{"statistic":{"FG":[],"G":{"I":"5ab11e35494765f3ca235393","T":"2015"},"LG":[{"A":{"I":"5abc977d494765f3cab7d801","T":"Китай (жен)","XI":13233},"D":1441452600,"H":{"I":"5abc977d494765f3cab7d82a","T":"Япония (жен)","XI":13725},"I":"5abc9d19494765f3cac983bb","P":[{"A":11,"H":23,"T":18},{"A":11,"H":21,"T":19},{"A":12,"H":24,"T":20},{"A":16,"H":17,"T":21}],"S1":85,"S2":50,"SI":"5abc9d19494765f3cac9839a","St":3},{"A":{"I":"5abc9781494765f3cab7f7d5","T":"Южная Корея (жен)","XI":35175},"D":1441445400,"H":{"I":"5abc9d16494765f3cac972b7","T":"Тайвань (жeн)","XI":35113},"I":"5abc9d19494765f3cac983ac","P":[{"A":13,"H":6,"T":18},{"A":14,"H":15,"T":19},{"A":19,"H":15,"T":20},{"A":6,"H":9,"T":21}],"S1":45,"S2":52,"SI":"5abc9d19494765f3cac9839a","St":3},{"A":{"I":"5abc9781494765f3cab7f7d5","T":"Южная Корея (жен)","XI":35175},"D":1441366200,"H":{"I":"5abc977d494765f3cab7d801","T":"Китай (жен)","XI":13233},"I":"5abc9d19494765f3cac983ad","P":[{"A":6,"H":19,"T":18},{"A":10,"H":12,"T":19},{"A":6,"H":16,"T":20},{"A":23,"H":13,"T":21}],"S1":60,"S2":45,"SI":"5abc9d19494765f3cac9839a","St":3},{"A":{"I":"5abc9d16494765f3cac972b7","T":"Тайвань (жeн)","XI":35113},"D":1441359000,"H":{"I":"5abc977d494765f3cab7d82a","T":"Япония (жен)","XI":13725},"I":"5abc9d19494765f3cac983d5","P":[{"A":11,"H":23,"T":18},{"A":22,"H":11,"T":19},{"A":13,"H":9,"T":20},{"A":12,"H":22,"T":21}],"S1":65,"S2":58,"SI":"5abc9d19494765f3cac9839a","St":3},{"A":{"I":"5abc9d17494765f3cac9793e","T":"Филиппины (жен)","XI":35189},"D":1441350000,"H":{"I":"5abc9d16494765f3cac96fa6","T":"Индия (жeн)","XI":35109},"I":"5abc9d19494765f3cac98403","P":[{"A":16,"H":22,"T":18},{"A":23,"H":15,"T":19},{"A":26,"H":16,"T":20},{"A":17,"H":23,"T":21}],"S1":76,"S2":82,"SI":"5abc9d19494765f3cac983f7","St":3},{"A":{"I":"5abc9d17494765f3cac9793d","T":"Северная Корея (жен)","XI":223379},"D":1441342800,"H":{"I":"5abc9d16494765f3cac96fae","T":"Таиланд (жен)","XI":35137},"I":"5abc9d19494765f3cac98400","P":[{"A":14,"H":14,"T":18},{"A":15,"H":10,"T":19},{"A":17,"H":11,"T":20},{"A":20,"H":15,"T":21}],"S1":50,"S2":66,"SI":"5abc9d19494765f3cac983f7","St":3},{"A":{"I":"5abc9d16494765f3cac972b7","T":"Тайвань (жeн)","XI":35113},"D":1441193400,"H":{"I":"5abc977d494765f3cab7d801","T":"Китай (жен)","XI":13233},"I":"5abc9d19494765f3cac982c2","P":[{"A":18,"H":18,"T":18},{"A":18,"H":26,"T":19},{"A":16,"H":16,"T":20},{"A":10,"H":16,"T":21}],"S1":76,"S2":62,"SI":"5abc9d19494765f3cac98296","St":3},{"A":{"I":"5abc977d494765f3cab7d82a","T":"Япония (жен)","XI":13725},"D":1441186200,"H":{"I":"5abc9d16494765f3cac96fae","T":"Таиланд (жен)","XI":35137},"I":"5abc9d19494765f3cac982c8","P":[{"A":26,"H":6,"T":18},{"A":24,"H":13,"T":19},{"A":18,"H":18,"T":20},{"A":27,"H":6,"T":21}],"S1":43,"S2":95,"SI":"5abc9d19494765f3cac98296","St":3},{"A":{"I":"5abc9781494765f3cab7f7d5","T":"Южная Корея (жен)","XI":35175},"D":1441177200,"H":{"I":"5abc9d16494765f3cac96fa6","T":"Индия (жeн)","XI":35109},"I":"5abc9d19494765f3cac982f0","P":[{"A":38,"H":13,"T":18},{"A":29,"H":7,"T":19},{"A":25,"H":12,"T":20},{"A":29,"H":12,"T":21}],"S1":44,"S2":121,"SI":"5abc9d19494765f3cac98296","St":3},{"A":{"I":"5abc9d19494765f3cac982d2","T":"Гонконг (жeн)","XI":35397},"D":1441170000,"H":{"I":"5abc9d17494765f3cac9793d","T":"Северная Корея (жен)","XI":223379},"I":"5abc9d19494765f3cac98327","P":[{"A":14,"H":16,"T":18},{"A":6,"H":20,"T":19},{"A":6,"H":13,"T":20},{"A":17,"H":17,"T":21}],"S1":66,"S2":43,"SI":"5abc9d19494765f3cac98296","St":3,"W":1}],"N":[{"I":"5ab11d65494765f3ca2315c8","T":"2017"},{"I":"5ab11e35494765f3ca235393","T":"2015"},{"I":"5ab12632494765f3ca23fb68","T":"2013"}],"S":[{"C":{"I":229,"T":"Азия"},"H":false,"I":"5abc9d19494765f3cac983f7","N":"Кубок Азии. Женщины","R":"5ab1275a494765f3ca242277","T":1,"D":{"C":[{"A":{"I":"5abc9d17494765f3cac9793d","T":"Северная Корея (жен)","XI":223379},"G":[{"A":{"I":"5abc9d17494765f3cac9793d","T":"Северная Корея (жен)","XI":223379},"D":1441342800,"H":{"I":"5abc9d16494765f3cac96fae","T":"Таиланд (жен)","XI":35137},"I":"5abc9d19494765f3cac98400","P":[{"A":14,"H":14,"T":18},{"A":15,"H":10,"T":19},{"A":17,"H":11,"T":20},{"A":20,"H":15,"T":21}],"S1":50,"S2":66,"SI":"5abc9d19494765f3cac983f7","St":3}],"H":{"I":"5abc9d16494765f3cac96fae","T":"Таиланд (жен)","XI":35137},"T":"Финал"},{"A":{"I":"5abc9d17494765f3cac9793e","T":"Филиппины (жен)","XI":35189},"G":[{"A":{"I":"5abc9d17494765f3cac9793e","T":"Филиппины (жен)","XI":35189},"D":1441350000,"H":{"I":"5abc9d16494765f3cac96fa6","T":"Индия (жeн)","XI":35109},"I":"5abc9d19494765f3cac98403","P":[{"A":16,"H":22,"T":18},{"A":23,"H":15,"T":19},{"A":26,"H":16,"T":20},{"A":17,"H":23,"T":21}],"S1":76,"S2":82,"SI":"5abc9d19494765f3cac983f7","St":3}],"H":{"I":"5abc9d16494765f3cac96fa6","T":"Индия (жeн)","XI":35109},"T":"Финал"}]}},{"C":{"I":229,"T":"Азия"},"H":false,"I":"5abc9d19494765f3cac9839a","N":"Кубок Азии. Женщины","R":"5ab1275a494765f3ca242277","T":1,"D":{"C":[{"A":{"I":"5abc977d494765f3cab7d801","T":"Китай (жен)","XI":13233},"C":{"A":{"I":"5abc9d16494765f3cac972b7","T":"Тайвань (жeн)","XI":35113},"G":[{"A":{"I":"5abc9d16494765f3cac972b7","T":"Тайвань (жeн)","XI":35113},"D":1441359000,"H":{"I":"5abc977d494765f3cab7d82a","T":"Япония (жен)","XI":13725},"I":"5abc9d19494765f3cac983d5","P":[{"A":11,"H":23,"T":18},{"A":22,"H":11,"T":19},{"A":13,"H":9,"T":20},{"A":12,"H":22,"T":21}],"S1":65,"S2":58,"SI":"5abc9d19494765f3cac9839a","St":3}],"H":{"I":"5abc977d494765f3cab7d82a","T":"Япония (жен)","XI":13725},"T":"Полуфиналы"},"D":{"A":{"I":"5abc9781494765f3cab7f7d5","T":"Южная Корея (жен)","XI":35175},"G":[{"A":{"I":"5abc9781494765f3cab7f7d5","T":"Южная Корея (жен)","XI":35175},"D":1441366200,"H":{"I":"5abc977d494765f3cab7d801","T":"Китай (жен)","XI":13233},"I":"5abc9d19494765f3cac983ad","P":[{"A":6,"H":19,"T":18},{"A":10,"H":12,"T":19},{"A":6,"H":16,"T":20},{"A":23,"H":13,"T":21}],"S1":60,"S2":45,"SI":"5abc9d19494765f3cac9839a","St":3}],"H":{"I":"5abc977d494765f3cab7d801","T":"Китай (жен)","XI":13233},"T":"Полуфиналы"},"G":[{"A":{"I":"5abc977d494765f3cab7d801","T":"Китай (жен)","XI":13233},"D":1441452600,"H":{"I":"5abc977d494765f3cab7d82a","T":"Япония (жен)","XI":13725},"I":"5abc9d19494765f3cac983bb","P":[{"A":11,"H":23,"T":18},{"A":11,"H":21,"T":19},{"A":12,"H":24,"T":20},{"A":16,"H":17,"T":21}],"S1":85,"S2":50,"SI":"5abc9d19494765f3cac9839a","St":3}],"H":{"I":"5abc977d494765f3cab7d82a","T":"Япония (жен)","XI":13725},"T":"Финал"},{"A":{"I":"5abc9781494765f3cab7f7d5","T":"Южная Корея (жен)","XI":35175},"G":[{"A":{"I":"5abc9781494765f3cab7f7d5","T":"Южная Корея (жен)","XI":35175},"D":1441445400,"H":{"I":"5abc9d16494765f3cac972b7","T":"Тайвань (жeн)","XI":35113},"I":"5abc9d19494765f3cac983ac","P":[{"A":13,"H":6,"T":18},{"A":14,"H":15,"T":19},{"A":19,"H":15,"T":20},{"A":6,"H":9,"T":21}],"S1":45,"S2":52,"SI":"5abc9d19494765f3cac9839a","St":3}],"H":{"I":"5abc9d16494765f3cac972b7","T":"Тайвань (жeн)","XI":35113},"T":"3-е место"}]}},{"C":{"I":229,"T":"Азия"},"H":false,"I":"5abc9d19494765f3cac98296","N":"Кубок Азии. Женщины","R":"5ab1275a494765f3ca242277","T":2,"A":{"C":[{"R":[{"C":5,"D":0,"F":0,"G":[{"A":{"I":"5abc977d494765f3cab7d82a","T":"Япония (жен)","XI":13725},"D":1441186200,"H":{"I":"5abc9d16494765f3cac96fae","T":"Таиланд (жен)","XI":35137},"I":"5abc9d19494765f3cac982c8","P":[{"A":26,"H":6,"T":18},{"A":24,"H":13,"T":19},{"A":18,"H":18,"T":20},{"A":27,"H":6,"T":21}],"R":1,"S1":43,"S2":95,"SI":"5abc9d19494765f3cac98296","St":3},{"A":{"I":"5abc977d494765f3cab7d801","T":"Китай (жен)","XI":13233},"D":1441107000,"H":{"I":"5abc977d494765f3cab7d82a","T":"Япония (жен)","XI":13725},"I":"5abc9d19494765f3cac9831f","P":[{"A":13,"H":18,"T":18},{"A":18,"H":19,"T":19},{"A":12,"H":8,"T":20},{"A":13,"H":12,"T":21}],"R":1,"S1":57,"S2":56,"SI":"5abc9d19494765f3cac98296","St":3},{"A":{"I":"5abc977d494765f3cab7d82a","T":"Япония (жен)","XI":13725},"D":1441013400,"H":{"I":"5abc9d16494765f3cac972b7","T":"Тайвань (жeн)","XI":35113},"I":"5abc9d19494765f3cac98344","P":[{"A":8,"H":15,"T":18},{"A":25,"H":8,"T":19},{"A":9,"H":15,"T":20},{"A":18,"H":6,"T":21}],"R":1,"S1":44,"S2":60,"SI":"5abc9d19494765f3cac98296","St":3},{"A":{"I":"5abc9d16494765f3cac96fa6","T":"Индия (жeн)","XI":35109},"D":1440927000,"H":{"I":"5abc977d494765f3cab7d82a","T":"Япония (жен)","XI":13725},"I":"5abc9d19494765f3cac982f1","P":[{"A":9,"H":32,"T":18},{"A":12,"H":31,"T":19},{"A":6,"H":25,"T":20},{"A":4,"H":43,"T":21}],"R":1,"S1":131,"S2":31,"SI":"5abc9d19494765f3cac98296","St":3},{"A":{"I":"5abc977d494765f3cab7d82a","T":"Япония (жен)","XI":13725},"D":1440840600,"H":{"I":"5abc9781494765f3cab7f7d5","T":"Южная Корея (жен)","XI":35175},"I":"5abc9d19494765f3cac982e9","P":[{"A":13,"H":13,"T":18},{"A":18,"H":17,"T":19},{"A":15,"H":15,"T":20},{"A":13,"H":8,"T":21}],"R":1,"S1":53,"S2":59,"SI":"5abc9d19494765f3cac98296","St":3}],"L":0,"M":1,"P":10,"S":0,"T":{"I":"5abc977d494765f3cab7d82a","T":"Япония (жен)","XI":13725},"W":5},{"C":5,"D":0,"F":0,"G":[{"A":{"I":"5abc9d16494765f3cac972b7","T":"Тайвань (жeн)","XI":35113},"D":1441193400,"H":{"I":"5abc977d494765f3cab7d801","T":"Китай (жен)","XI":13233},"I":"5abc9d19494765f3cac982c2","P":[{"A":18,"H":18,"T":18},{"A":18,"H":26,"T":19},{"A":16,"H":16,"T":20},{"A":10,"H":16,"T":21}],"R":1,"S1":76,"S2":62,"SI":"5abc9d19494765f3cac98296","St":3},{"A":{"I":"5abc977d494765f3cab7d801","T":"Китай (жен)","XI":13233},"D":1441107000,"H":{"I":"5abc977d494765f3cab7d82a","T":"Япония (жен)","XI":13725},"I":"5abc9d19494765f3cac9831f","P":[{"A":13,"H":18,"T":18},{"A":18,"H":19,"T":19},{"A":12,"H":8,"T":20},{"A":13,"H":12,"T":21}],"R":2,"S1":57,"S2":56,"SI":"5abc9d19494765f3cac98296","St":3},{"A":{"I":"5abc9d16494765f3cac96fa6","T":"Индия (жeн)","XI":35109},"D":1441020600,"H":{"I":"5abc977d494765f3cab7d801","T":"Китай (жен)","XI":13233},"I":"5abc9d19494765f3cac982c6","P":[{"A":4,"H":29,"T":18},{"A":11,"H":18,"T":19},{"A":20,"H":35,"T":20},{"A":4,"H":20,"T":21}],"R":1,"S1":102,"S2":39,"SI":"5abc9d19494765f3cac98296","St":3},{"A":{"I":"5abc977d494765f3cab7d801","T":"Китай (жен)","XI":13233},"D":1440934200,"H":{"I":"5abc9781494765f3cab7f7d5","T":"Южная Корея (жен)","XI":35175},"I":"5abc9d19494765f3cac98366","P":[{"A":15,"H":18,"T":18},{"A":12,"H":11,"T":19},{"A":23,"H":15,"T":20},{"A":24,"H":14,"T":21}],"R":1,"S1":58,"S2":74,"SI":"5abc9d19494765f3cac98296","St":3},{"A":{"I":"5abc977d494765f3cab7d801","T":"Китай (жен)","XI":13233},"D":1440847800,"H":{"I":"5abc9d16494765f3cac96fae","T":"Таиланд (жен)","XI":35137},"I":"5abc9d19494765f3cac98354","P":[{"A":28,"H":9,"T":18},{"A":27,"H":6,"T":19},{"A":23,"H":14,"T":20},{"A":35,"H":5,"T":21}],"R":1,"S1":34,"S2":113,"SI":"5abc9d19494765f3cac98296","St":3}],"L":1,"M":2,"P":9,"S":0,"T":{"I":"5abc977d494765f3cab7d801","T":"Китай (жен)","XI":13233},"W":4},{"C":5,"D":0,"F":0,"G":[{"A":{"I":"5abc9781494765f3cab7f7d5","T":"Южная Корея (жен)","XI":35175},"D":1441177200,"H":{"I":"5abc9d16494765f3cac96fa6","T":"Индия (жeн)","XI":35109},"I":"5abc9d19494765f3cac982f0","P":[{"A":38,"H":13,"T":18},{"A":29,"H":7,"T":19},{"A":25,"H":12,"T":20},{"A":29,"H":12,"T":21}],"R":1,"S1":44,"S2":121,"SI":"5abc9d19494765f3cac98296","St":3},{"A":{"I":"5abc9d16494765f3cac972b7","T":"Тайвань (жeн)","XI":35113},"D":1441099800,"H":{"I":"5abc9781494765f3cab7f7d5","T":"Южная Корея (жен)","XI":35175},"I":"5abc9d19494765f3cac98360","P":[{"A":8,"H":24,"T":18},{"A":12,"H":8,"T":19},{"A":13,"H":26,"T":20},{"A":25,"H":18,"T":21}],"R":1,"S1":76,"S2":58,"SI":"5abc9d19494765f3cac98296","St":3},{"A":{"I":"5abc9781494765f3cab7f7d5","T":"Южная Корея (жен)","XI":35175},"D":1441004400,"H":{"I":"5abc9d16494765f3cac96fae","T":"Таиланд (жен)","XI":35137},"I":"5abc9d19494765f3cac982ea","P":[{"A":23,"H":9,"T":18},{"A":22,"H":8,"T":19},{"A":25,"H":11,"T":20},{"A":27,"H":13,"T":21}],"R":1,"S1":41,"S2":97,"SI":"5abc9d19494765f3cac98296","St":3},{"A":{"I":"5abc977d494765f3cab7d801","T":"Китай (жен)","XI":13233},"D":1440934200,"H":{"I":"5abc9781494765f3cab7f7d5","T":"Южная Корея (жен)","XI":35175},"I":"5abc9d19494765f3cac98366","P":[{"A":15,"H":18,"T":18},{"A":12,"H":11,"T":19},{"A":23,"H":15,"T":20},{"A":24,"H":14,"T":21}],"R":2,"S1":58,"S2":74,"SI":"5abc9d19494765f3cac98296","St":3},{"A":{"I":"5abc977d494765f3cab7d82a","T":"Япония (жен)","XI":13725},"D":1440840600,"H":{"I":"5abc9781494765f3cab7f7d5","T":"Южная Корея (жен)","XI":35175},"I":"5abc9d19494765f3cac982e9","P":[{"A":13,"H":13,"T":18},{"A":18,"H":17,"T":19},{"A":15,"H":15,"T":20},{"A":13,"H":8,"T":21}],"R":2,"S1":53,"S2":59,"SI":"5abc9d19494765f3cac98296","St":3}],"L":2,"M":3,"P":8,"S":0,"T":{"I":"5abc9781494765f3cab7f7d5","T":"Южная Корея (жен)","XI":35175},"W":3},{"C":5,"D":0,"F":0,"G":[{"A":{"I":"5abc9d16494765f3cac972b7","T":"Тайвань (жeн)","XI":35113},"D":1441193400,"H":{"I":"5abc977d494765f3cab7d801","T":"Китай (жен)","XI":13233},"I":"5abc9d19494765f3cac982c2","P":[{"A":18,"H":18,"T":18},{"A":18,"H":26,"T":19},{"A":16,"H":16,"T":20},{"A":10,"H":16,"T":21}],"R":2,"S1":76,"S2":62,"SI":"5abc9d19494765f3cac98296","St":3},{"A":{"I":"5abc9d16494765f3cac972b7","T":"Тайвань (жeн)","XI":35113},"D":1441099800,"H":{"I":"5abc9781494765f3cab7f7d5","T":"Южная Корея (жен)","XI":35175},"I":"5abc9d19494765f3cac98360","P":[{"A":8,"H":24,"T":18},{"A":12,"H":8,"T":19},{"A":13,"H":26,"T":20},{"A":25,"H":18,"T":21}],"R":2,"S1":76,"S2":58,"SI":"5abc9d19494765f3cac98296","St":3},{"A":{"I":"5abc977d494765f3cab7d82a","T":"Япония (жен)","XI":13725},"D":1441013400,"H":{"I":"5abc9d16494765f3cac972b7","T":"Тайвань (жeн)","XI":35113},"I":"5abc9d19494765f3cac98344","P":[{"A":8,"H":15,"T":18},{"A":25,"H":8,"T":19},{"A":9,"H":15,"T":20},{"A":18,"H":6,"T":21}],"R":2,"S1":44,"S2":60,"SI":"5abc9d19494765f3cac98296","St":3},{"A":{"I":"5abc9d16494765f3cac96fae","T":"Таиланд (жен)","XI":35137},"D":1440918000,"H":{"I":"5abc9d16494765f3cac972b7","T":"Тайвань (жeн)","XI":35113},"I":"5abc9d19494765f3cac982eb","P":[{"A":10,"H":23,"T":18},{"A":8,"H":32,"T":19},{"A":8,"H":32,"T":20},{"A":16,"H":26,"T":21}],"R":1,"S1":113,"S2":42,"SI":"5abc9d19494765f3cac98296","St":3},{"A":{"I":"5abc9d16494765f3cac96fa6","T":"Индия (жeн)","XI":35109},"D":1440831600,"H":{"I":"5abc9d16494765f3cac972b7","T":"Тайвань (жeн)","XI":35113},"I":"5abc9d19494765f3cac98337","P":[{"A":11,"H":22,"T":18},{"A":14,"H":15,"T":19},{"A":18,"H":29,"T":20},{"A":18,"H":26,"T":21}],"R":1,"S1":92,"S2":61,"SI":"5abc9d19494765f3cac98296","St":3}],"L":3,"M":4,"P":7,"S":0,"T":{"I":"5abc9d16494765f3cac972b7","T":"Тайвань (жeн)","XI":35113},"W":2},{"C":5,"D":0,"F":0,"G":[{"A":{"I":"5abc977d494765f3cab7d82a","T":"Япония (жен)","XI":13725},"D":1441186200,"H":{"I":"5abc9d16494765f3cac96fae","T":"Таиланд (жен)","XI":35137},"I":"5abc9d19494765f3cac982c8","P":[{"A":26,"H":6,"T":18},{"A":24,"H":13,"T":19},{"A":18,"H":18,"T":20},{"A":27,"H":6,"T":21}],"R":2,"S1":43,"S2":95,"SI":"5abc9d19494765f3cac98296","St":3},{"A":{"I":"5abc9d16494765f3cac96fae","T":"Таиланд (жен)","XI":35137},"D":1441090800,"H":{"I":"5abc9d16494765f3cac96fa6","T":"Индия (жeн)","XI":35109},"I":"5abc9d19494765f3cac98345","P":[{"A":21,"H":14,"T":18},{"A":14,"H":17,"T":19},{"A":13,"H":17,"T":20},{"A":17,"H":15,"T":21}],"R":1,"S1":63,"S2":65,"SI":"5abc9d19494765f3cac98296","St":3},{"A":{"I":"5abc9781494765f3cab7f7d5","T":"Южная Корея (жен)","XI":35175},"D":1441004400,"H":{"I":"5abc9d16494765f3cac96fae","T":"Таиланд (жен)","XI":35137},"I":"5abc9d19494765f3cac982ea","P":[{"A":23,"H":9,"T":18},{"A":22,"H":8,"T":19},{"A":25,"H":11,"T":20},{"A":27,"H":13,"T":21}],"R":2,"S1":41,"S2":97,"SI":"5abc9d19494765f3cac98296","St":3},{"A":{"I":"5abc9d16494765f3cac96fae","T":"Таиланд (жен)","XI":35137},"D":1440918000,"H":{"I":"5abc9d16494765f3cac972b7","T":"Тайвань (жeн)","XI":35113},"I":"5abc9d19494765f3cac982eb","P":[{"A":10,"H":23,"T":18},{"A":8,"H":32,"T":19},{"A":8,"H":32,"T":20},{"A":16,"H":26,"T":21}],"R":2,"S1":113,"S2":42,"SI":"5abc9d19494765f3cac98296","St":3},{"A":{"I":"5abc977d494765f3cab7d801","T":"Китай (жен)","XI":13233},"D":1440847800,"H":{"I":"5abc9d16494765f3cac96fae","T":"Таиланд (жен)","XI":35137},"I":"5abc9d19494765f3cac98354","P":[{"A":28,"H":9,"T":18},{"A":27,"H":6,"T":19},{"A":23,"H":14,"T":20},{"A":35,"H":5,"T":21}],"R":2,"S1":34,"S2":113,"SI":"5abc9d19494765f3cac98296","St":3}],"L":4,"M":5,"P":6,"S":0,"T":{"I":"5abc9d16494765f3cac96fae","T":"Таиланд (жен)","XI":35137},"W":1},{"C":5,"D":0,"F":0,"G":[{"A":{"I":"5abc9781494765f3cab7f7d5","T":"Южная Корея (жен)","XI":35175},"D":1441177200,"H":{"I":"5abc9d16494765f3cac96fa6","T":"Индия (жeн)","XI":35109},"I":"5abc9d19494765f3cac982f0","P":[{"A":38,"H":13,"T":18},{"A":29,"H":7,"T":19},{"A":25,"H":12,"T":20},{"A":29,"H":12,"T":21}],"R":2,"S1":44,"S2":121,"SI":"5abc9d19494765f3cac98296","St":3},{"A":{"I":"5abc9d16494765f3cac96fae","T":"Таиланд (жен)","XI":35137},"D":1441090800,"H":{"I":"5abc9d16494765f3cac96fa6","T":"Индия (жeн)","XI":35109},"I":"5abc9d19494765f3cac98345","P":[{"A":21,"H":14,"T":18},{"A":14,"H":17,"T":19},{"A":13,"H":17,"T":20},{"A":17,"H":15,"T":21}],"R":2,"S1":63,"S2":65,"SI":"5abc9d19494765f3cac98296","St":3},{"A":{"I":"5abc9d16494765f3cac96fa6","T":"Индия (жeн)","XI":35109},"D":1441020600,"H":{"I":"5abc977d494765f3cab7d801","T":"Китай (жен)","XI":13233},"I":"5abc9d19494765f3cac982c6","P":[{"A":4,"H":29,"T":18},{"A":11,"H":18,"T":19},{"A":20,"H":35,"T":20},{"A":4,"H":20,"T":21}],"R":2,"S1":102,"S2":39,"SI":"5abc9d19494765f3cac98296","St":3},{"A":{"I":"5abc9d16494765f3cac96fa6","T":"Индия (жeн)","XI":35109},"D":1440927000,"H":{"I":"5abc977d494765f3cab7d82a","T":"Япония (жен)","XI":13725},"I":"5abc9d19494765f3cac982f1","P":[{"A":9,"H":32,"T":18},{"A":12,"H":31,"T":19},{"A":6,"H":25,"T":20},{"A":4,"H":43,"T":21}],"R":2,"S1":131,"S2":31,"SI":"5abc9d19494765f3cac98296","St":3},{"A":{"I":"5abc9d16494765f3cac96fa6","T":"Индия (жeн)","XI":35109},"D":1440831600,"H":{"I":"5abc9d16494765f3cac972b7","T":"Тайвань (жeн)","XI":35113},"I":"5abc9d19494765f3cac98337","P":[{"A":11,"H":22,"T":18},{"A":14,"H":15,"T":19},{"A":18,"H":29,"T":20},{"A":18,"H":26,"T":21}],"R":2,"S1":92,"S2":61,"SI":"5abc9d19494765f3cac98296","St":3}],"L":5,"M":6,"P":5,"S":0,"T":{"I":"5abc9d16494765f3cac96fa6","T":"Индия (жeн)","XI":35109},"W":0}],"T":"Группа A"},{"R":[{"C":5,"D":0,"F":0,"G":[{"A":{"I":"5abc9d17494765f3cac9793e","T":"Филиппины (жен)","XI":35189},"D":1441155600,"H":{"I":"5abc9d16494765f3cac96fa8","T":"Казахстан (жен)","XI":35085},"I":"5abc9d19494765f3cac982ed","P":[{"A":20,"H":23,"T":18},{"A":13,"H":9,"T":19},{"A":16,"H":23,"T":20},{"A":14,"H":8,"T":21},{"A":17,"H":10,"T":4}],"R":1,"S1":73,"S2":80,"SI":"5abc9d19494765f3cac98296","St":3},{"A":{"I":"5abc9d19494765f3cac982d2","T":"Гонконг (жeн)","XI":35397},"D":1441076400,"H":{"I":"5abc9d17494765f3cac9793e","T":"Филиппины (жен)","XI":35189},"I":"5abc9d19494765f3cac982ef","P":[{"A":15,"H":16,"T":18},{"A":13,"H":26,"T":19},{"A":17,"H":21,"T":20},{"A":17,"H":12,"T":21}],"R":1,"S1":75,"S2":62,"SI":"5abc9d19494765f3cac98296","St":3},{"A":{"I":"5abc9d17494765f3cac9793e","T":"Филиппины (жен)","XI":35189},"D":1440982800,"H":{"I":"5abc9d19494765f3cac982d0","T":"Шри-Ланка (жен)","XI":223377},"I":"5abc9d19494765f3cac98320","P":[{"A":14,"H":14,"T":18},{"A":22,"H":6,"T":19},{"A":10,"H":9,"T":20},{"A":19,"H":16,"T":21}],"R":1,"S1":45,"S2":65,"SI":"5abc9d19494765f3cac98296","St":3},{"A":{"I":"5abc9d17494765f3cac9793d","T":"Северная Корея (жен)","XI":223379},"D":1440910800,"H":{"I":"5abc9d17494765f3cac9793e","T":"Филиппины (жен)","XI":35189},"I":"5abc9d19494765f3cac98311","P":[{"A":16,"H":7,"T":18},{"A":19,"H":23,"T":19},{"A":17,"H":14,"T":20},{"A":15,"H":24,"T":21}],"R":1,"S1":68,"S2":67,"SI":"5abc9d19494765f3cac98296","St":3},{"A":{"I":"5abc9d16494765f3cac96faf","T":"Малайзия (жeн)","XI":35069},"D":1440817200,"H":{"I":"5abc9d17494765f3cac9793e","T":"Филиппины (жен)","XI":35189},"I":"5abc9d19494765f3cac982ee","P":[{"A":14,"H":11,"T":18},{"A":17,"H":14,"T":19},{"A":24,"H":21,"T":20},{"A":16,"H":18,"T":21}],"R":2,"S1":64,"S2":71,"SI":"5abc9d19494765f3cac98296","St":3}],"L":1,"M":1,"P":9,"S":0,"T":{"I":"5abc9d17494765f3cac9793e","T":"Филиппины (жен)","XI":35189},"W":3},{"C":5,"D":0,"F":0,"G":[{"A":{"I":"5abc9d19494765f3cac982d2","T":"Гонконг (жeн)","XI":35397},"D":1441170000,"H":{"I":"5abc9d17494765f3cac9793d","T":"Северная Корея (жен)","XI":223379},"I":"5abc9d19494765f3cac98327","P":[{"A":14,"H":16,"T":18},{"A":6,"H":20,"T":19},{"A":6,"H":13,"T":20},{"A":17,"H":17,"T":21}],"R":1,"S1":66,"S2":43,"SI":"5abc9d19494765f3cac98296","St":3,"W":1},{"A":{"I":"5abc9d17494765f3cac9793d","T":"Северная Корея (жен)","XI":223379},"D":1441083600,"H":{"I":"5abc9d16494765f3cac96faf","T":"Малайзия (жeн)","XI":35069},"I":"5abc9d19494765f3cac982c7","P":[{"A":23,"H":12,"T":18},{"A":20,"H":9,"T":19},{"A":19,"H":11,"T":20},{"A":21,"H":13,"T":21}],"R":1,"S1":45,"S2":83,"SI":"5abc9d19494765f3cac98296","St":3},{"A":{"I":"5abc9d16494765f3cac96fa8","T":"Казахстан (жен)","XI":35085},"D":1440997200,"H":{"I":"5abc9d17494765f3cac9793d","T":"Северная Корея (жен)","XI":223379},"I":"5abc9d19494765f3cac98357","P":[{"A":13,"H":25,"T":18},{"A":11,"H":15,"T":19},{"A":11,"H":13,"T":20},{"A":20,"H":15,"T":21}],"R":1,"S1":68,"S2":55,"SI":"5abc9d19494765f3cac98296","St":3,"W":1},{"A":{"I":"5abc9d17494765f3cac9793d","T":"Северная Корея (жен)","XI":223379},"D":1440910800,"H":{"I":"5abc9d17494765f3cac9793e","T":"Филиппины (жен)","XI":35189},"I":"5abc9d19494765f3cac98311","P":[{"A":16,"H":7,"T":18},{"A":19,"H":23,"T":19},{"A":17,"H":14,"T":20},{"A":15,"H":24,"T":21}],"R":2,"S1":68,"S2":67,"SI":"5abc9d19494765f3cac98296","St":3},{"A":{"I":"5abc9d17494765f3cac9793d","T":"Северная Корея (жен)","XI":223379},"D":1440824400,"H":{"I":"5abc9d19494765f3cac982d0","T":"Шри-Ланка (жен)","XI":223377},"I":"5abc9d19494765f3cac98328","P":[{"A":25,"H":8,"T":18},{"A":20,"H":14,"T":19},{"A":16,"H":9,"T":20},{"A":21,"H":4,"T":21}],"R":1,"S1":35,"S2":82,"SI":"5abc9d19494765f3cac98296","St":3,"W":2}],"L":1,"M":2,"P":9,"S":0,"T":{"I":"5abc9d17494765f3cac9793d","T":"Северная Корея (жен)","XI":223379},"W":4},{"C":5,"D":0,"F":0,"G":[{"A":{"I":"5abc9d17494765f3cac9793e","T":"Филиппины (жен)","XI":35189},"D":1441155600,"H":{"I":"5abc9d16494765f3cac96fa8","T":"Казахстан (жен)","XI":35085},"I":"5abc9d19494765f3cac982ed","P":[{"A":20,"H":23,"T":18},{"A":13,"H":9,"T":19},{"A":16,"H":23,"T":20},{"A":14,"H":8,"T":21},{"A":17,"H":10,"T":4}],"R":2,"S1":73,"S2":80,"SI":"5abc9d19494765f3cac98296","St":3},{"A":{"I":"5abc9d19494765f3cac982d0","T":"Шри-Ланка (жен)","XI":223377},"D":1441069200,"H":{"I":"5abc9d16494765f3cac96fa8","T":"Казахстан (жен)","XI":35085},"I":"5abc9d19494765f3cac9833d","P":[{"A":9,"H":21,"T":18},{"A":22,"H":18,"T":19},{"A":11,"H":22,"T":20},{"A":8,"H":17,"T":21}],"R":1,"S1":78,"S2":50,"SI":"5abc9d19494765f3cac98296","St":3,"W":1},{"A":{"I":"5abc9d16494765f3cac96fa8","T":"Казахстан (жен)","XI":35085},"D":1440997200,"H":{"I":"5abc9d17494765f3cac9793d","T":"Северная Корея (жен)","XI":223379},"I":"5abc9d19494765f3cac98357","P":[{"A":13,"H":25,"T":18},{"A":11,"H":15,"T":19},{"A":11,"H":13,"T":20},{"A":20,"H":15,"T":21}],"R":2,"S1":68,"S2":55,"SI":"5abc9d19494765f3cac98296","St":3,"W":1},{"A":{"I":"5abc9d16494765f3cac96fa8","T":"Казахстан (жен)","XI":35085},"D":1440903600,"H":{"I":"5abc9d16494765f3cac96faf","T":"Малайзия (жeн)","XI":35069},"I":"5abc9d19494765f3cac982d5","P":[{"A":14,"H":20,"T":18},{"A":18,"H":11,"T":19},{"A":18,"H":7,"T":20},{"A":23,"H":27,"T":21}],"R":1,"S1":65,"S2":73,"SI":"5abc9d19494765f3cac98296","St":3},{"A":{"I":"5abc9d16494765f3cac96fa8","T":"Казахстан (жен)","XI":35085},"D":1440810000,"H":{"I":"5abc9d19494765f3cac982d2","T":"Гонконг (жeн)","XI":35397},"I":"5abc9d19494765f3cac9833e","P":[{"A":30,"H":13,"T":18},{"A":19,"H":12,"T":19},{"A":22,"H":11,"T":20},{"A":28,"H":12,"T":21}],"R":1,"S1":48,"S2":99,"SI":"5abc9d19494765f3cac98296","St":3,"W":2}],"L":1,"M":3,"P":8,"S":0,"T":{"I":"5abc9d16494765f3cac96fa8","T":"Казахстан (жен)","XI":35085},"W":3},{"C":5,"D":0,"F":0,"G":[{"A":{"I":"5abc9d16494765f3cac96faf","T":"Малайзия (жeн)","XI":35069},"D":1441162800,"H":{"I":"5abc9d19494765f3cac982d0","T":"Шри-Ланка (жен)","XI":223377},"I":"5abc9d19494765f3cac982ec","P":[{"A":18,"H":5,"T":18},{"A":11,"H":7,"T":19},{"A":12,"H":12,"T":20},{"A":16,"H":9,"T":21}],"R":1,"S1":33,"S2":57,"SI":"5abc9d19494765f3cac98296","St":3},{"A":{"I":"5abc9d17494765f3cac9793d","T":"Северная Корея (жен)","XI":223379},"D":1441083600,"H":{"I":"5abc9d16494765f3cac96faf","T":"Малайзия (жeн)","XI":35069},"I":"5abc9d19494765f3cac982c7","P":[{"A":23,"H":12,"T":18},{"A":20,"H":9,"T":19},{"A":19,"H":11,"T":20},{"A":21,"H":13,"T":21}],"R":2,"S1":45,"S2":83,"SI":"5abc9d19494765f3cac98296","St":3},{"A":{"I":"5abc9d16494765f3cac96faf","T":"Малайзия (жeн)","XI":35069},"D":1440990000,"H":{"I":"5abc9d19494765f3cac982d2","T":"Гонконг (жeн)","XI":35397},"I":"5abc9d19494765f3cac9832d","P":[{"A":12,"H":14,"T":18},{"A":29,"H":11,"T":19},{"A":14,"H":17,"T":20},{"A":23,"H":19,"T":21}],"R":1,"S1":61,"S2":78,"SI":"5abc9d19494765f3cac98296","St":3},{"A":{"I":"5abc9d16494765f3cac96fa8","T":"Казахстан (жен)","XI":35085},"D":1440903600,"H":{"I":"5abc9d16494765f3cac96faf","T":"Малайзия (жeн)","XI":35069},"I":"5abc9d19494765f3cac982d5","P":[{"A":14,"H":20,"T":18},{"A":18,"H":11,"T":19},{"A":18,"H":7,"T":20},{"A":23,"H":27,"T":21}],"R":2,"S1":65,"S2":73,"SI":"5abc9d19494765f3cac98296","St":3},{"A":{"I":"5abc9d16494765f3cac96faf","T":"Малайзия (жeн)","XI":35069},"D":1440817200,"H":{"I":"5abc9d17494765f3cac9793e","T":"Филиппины (жен)","XI":35189},"I":"5abc9d19494765f3cac982ee","P":[{"A":14,"H":11,"T":18},{"A":17,"H":14,"T":19},{"A":24,"H":21,"T":20},{"A":16,"H":18,"T":21}],"R":1,"S1":64,"S2":71,"SI":"5abc9d19494765f3cac98296","St":3}],"L":2,"M":4,"P":8,"S":0,"T":{"I":"5abc9d16494765f3cac96faf","T":"Малайзия (жeн)","XI":35069},"W":3},{"C":5,"D":0,"F":0,"G":[{"A":{"I":"5abc9d19494765f3cac982d2","T":"Гонконг (жeн)","XI":35397},"D":1441170000,"H":{"I":"5abc9d17494765f3cac9793d","T":"Северная Корея (жен)","XI":223379},"I":"5abc9d19494765f3cac98327","P":[{"A":14,"H":16,"T":18},{"A":6,"H":20,"T":19},{"A":6,"H":13,"T":20},{"A":17,"H":17,"T":21}],"R":2,"S1":66,"S2":43,"SI":"5abc9d19494765f3cac98296","St":3,"W":1},{"A":{"I":"5abc9d19494765f3cac982d2","T":"Гонконг (жeн)","XI":35397},"D":1441076400,"H":{"I":"5abc9d17494765f3cac9793e","T":"Филиппины (жен)","XI":35189},"I":"5abc9d19494765f3cac982ef","P":[{"A":15,"H":16,"T":18},{"A":13,"H":26,"T":19},{"A":17,"H":21,"T":20},{"A":17,"H":12,"T":21}],"R":2,"S1":75,"S2":62,"SI":"5abc9d19494765f3cac98296","St":3},{"A":{"I":"5abc9d16494765f3cac96faf","T":"Малайзия (жeн)","XI":35069},"D":1440990000,"H":{"I":"5abc9d19494765f3cac982d2","T":"Гонконг (жeн)","XI":35397},"I":"5abc9d19494765f3cac9832d","P":[{"A":12,"H":14,"T":18},{"A":29,"H":11,"T":19},{"A":14,"H":17,"T":20},{"A":23,"H":19,"T":21}],"R":2,"S1":61,"S2":78,"SI":"5abc9d19494765f3cac98296","St":3},{"A":{"I":"5abc9d19494765f3cac982d0","T":"Шри-Ланка (жен)","XI":223377},"D":1440896400,"H":{"I":"5abc9d19494765f3cac982d2","T":"Гонконг (жeн)","XI":35397},"I":"5abc9d19494765f3cac9833f","P":[{"A":17,"H":17,"T":18},{"A":18,"H":21,"T":19},{"A":5,"H":26,"T":20},{"A":12,"H":8,"T":21}],"R":1,"S1":72,"S2":52,"SI":"5abc9d19494765f3cac98296","St":3,"W":1},{"A":{"I":"5abc9d16494765f3cac96fa8","T":"Казахстан (жен)","XI":35085},"D":1440810000,"H":{"I":"5abc9d19494765f3cac982d2","T":"Гонконг (жeн)","XI":35397},"I":"5abc9d19494765f3cac9833e","P":[{"A":30,"H":13,"T":18},{"A":19,"H":12,"T":19},{"A":22,"H":11,"T":20},{"A":28,"H":12,"T":21}],"R":2,"S1":48,"S2":99,"SI":"5abc9d19494765f3cac98296","St":3,"W":2}],"L":4,"M":5,"P":6,"S":0,"T":{"I":"5abc9d19494765f3cac982d2","T":"Гонконг (жeн)","XI":35397},"W":1},{"C":5,"D":0,"F":0,"G":[{"A":{"I":"5abc9d16494765f3cac96faf","T":"Малайзия (жeн)","XI":35069},"D":1441162800,"H":{"I":"5abc9d19494765f3cac982d0","T":"Шри-Ланка (жен)","XI":223377},"I":"5abc9d19494765f3cac982ec","P":[{"A":18,"H":5,"T":18},{"A":11,"H":7,"T":19},{"A":12,"H":12,"T":20},{"A":16,"H":9,"T":21}],"R":2,"S1":33,"S2":57,"SI":"5abc9d19494765f3cac98296","St":3},{"A":{"I":"5abc9d19494765f3cac982d0","T":"Шри-Ланка (жен)","XI":223377},"D":1441069200,"H":{"I":"5abc9d16494765f3cac96fa8","T":"Казахстан (жен)","XI":35085},"I":"5abc9d19494765f3cac9833d","P":[{"A":9,"H":21,"T":18},{"A":22,"H":18,"T":19},{"A":11,"H":22,"T":20},{"A":8,"H":17,"T":21}],"R":2,"S1":78,"S2":50,"SI":"5abc9d19494765f3cac98296","St":3,"W":1},{"A":{"I":"5abc9d17494765f3cac9793e","T":"Филиппины (жен)","XI":35189},"D":1440982800,"H":{"I":"5abc9d19494765f3cac982d0","T":"Шри-Ланка (жен)","XI":223377},"I":"5abc9d19494765f3cac98320","P":[{"A":14,"H":14,"T":18},{"A":22,"H":6,"T":19},{"A":10,"H":9,"T":20},{"A":19,"H":16,"T":21}],"R":2,"S1":45,"S2":65,"SI":"5abc9d19494765f3cac98296","St":3},{"A":{"I":"5abc9d19494765f3cac982d0","T":"Шри-Ланка (жен)","XI":223377},"D":1440896400,"H":{"I":"5abc9d19494765f3cac982d2","T":"Гонконг (жeн)","XI":35397},"I":"5abc9d19494765f3cac9833f","P":[{"A":17,"H":17,"T":18},{"A":18,"H":21,"T":19},{"A":5,"H":26,"T":20},{"A":12,"H":8,"T":21}],"R":2,"S1":72,"S2":52,"SI":"5abc9d19494765f3cac98296","St":3,"W":1},{"A":{"I":"5abc9d17494765f3cac9793d","T":"Северная Корея (жен)","XI":223379},"D":1440824400,"H":{"I":"5abc9d19494765f3cac982d0","T":"Шри-Ланка (жен)","XI":223377},"I":"5abc9d19494765f3cac98328","P":[{"A":25,"H":8,"T":18},{"A":20,"H":14,"T":19},{"A":16,"H":9,"T":20},{"A":21,"H":4,"T":21}],"R":2,"S1":35,"S2":82,"SI":"5abc9d19494765f3cac98296","St":3,"W":2}],"L":5,"M":6,"P":5,"S":0,"T":{"I":"5abc9d19494765f3cac982d0","T":"Шри-Ланка (жен)","XI":223377},"W":0}],"T":"Группа B"}]}}],"SI":3,"T":{"I":"5abc9d16494765f3cac96f9d","T":"Asia Cup Women"}},"t":{"255":"Этап","68":"Сезон","126":"Шахматка","42":"Турнирная таблица","389":"Информация","1":"Следующие матчи","2":"Предыдущие матчи","43":"Турнирная сетка","150":"Выберите сезон","44":"И ","45":"Игр","46":"В ","47":"Выигрыши","48":"Н ","49":"Ничья","50":"П ","51":"Поражений","52":"ЗМ","53":"Забито мячей","54":"ПМ","55":"Пропущено мячей","56":"РМ","57":"Разница мячей","58":"Очки","59":"Форма","60":"Команда","61":"Все","62":"Свернуть"}}