{"statistic":{"FG":[],"G":{"I":"5ab11d61494765f3ca231596","T":"2010"},"LG":[{"A":{"I":"5abc9ccf494765f3cac7c66f","T":"Литва (16)","XI":24907},"D":1281898800,"H":{"I":"5abc9ccf494765f3cac7c66c","T":"Хорватия (16)","XI":24843},"I":"5abc9cd5494765f3cac8087c","P":[{"A":6,"H":30,"T":18},{"A":26,"H":17,"T":19},{"A":7,"H":18,"T":20},{"A":13,"H":15,"T":21}],"S1":80,"S2":52,"SI":"5abc9cd5494765f3cac80869","St":3,"T":"Финал","W":1},{"A":{"I":"5abc9ccf494765f3cac7c664","T":"Турция (16)","XI":22265},"D":1281890700,"H":{"I":"5abc9ccf494765f3cac7c666","T":"Испания (16)","XI":24855},"I":"5abc9cd5494765f3cac8087b","P":[{"A":25,"H":17,"T":18},{"A":18,"H":13,"T":19},{"A":16,"H":17,"T":20},{"A":16,"H":17,"T":21}],"S1":64,"S2":75,"SI":"5abc9cd5494765f3cac80869","St":3,"W":2},{"A":{"I":"5abc9ccf494765f3cac7c569","T":"Латвия (16)","XI":22263},"D":1281882600,"H":{"I":"5abc9ccf494765f3cac7c6ae","T":"Израиль (16)","XI":25015},"I":"5abc9cd4494765f3cac7fcc4","P":[{"A":15,"H":17,"T":18},{"A":18,"H":11,"T":19},{"A":14,"H":12,"T":20},{"A":18,"H":22,"T":21}],"S1":62,"S2":65,"SI":"5abc9cd3494765f3cac7fc38","St":3},{"A":{"I":"5abc9ccf494765f3cac7c56b","T":"Германия (16)","XI":24791},"D":1281874500,"H":{"I":"5abc9cd1494765f3cac7d9cb","T":"Дания (16)","XI":25579},"I":"5abc9cd4494765f3cac7fc50","P":[{"A":18,"H":24,"T":18},{"A":17,"H":21,"T":19},{"A":18,"H":12,"T":20},{"A":19,"H":20,"T":21}],"S1":77,"S2":72,"SI":"5abc9cd3494765f3cac7fc38","St":3,"W":1},{"A":{"I":"5abc9ccf494765f3cac7c56c","T":"Сербия (16)","XI":24909},"D":1281871800,"DI":"За 5-6 места.","H":{"I":"5abc9ccf494765f3cac7c605","T":"Франция (16)","XI":24911},"I":"5abc9cd3494765f3cac7fbc5","P":[{"A":17,"H":10,"T":18},{"A":15,"H":9,"T":19},{"A":13,"H":14,"T":20},{"A":10,"H":12,"T":21}],"S1":45,"S2":55,"SI":"5abc9cd3494765f3cac7fbb4","St":3,"T":"5-е место","W":2},{"A":{"I":"5abc9ccf494765f3cac7c5fd","T":"Черногория (16)","XI":24847},"D":1281863700,"DI":"За 7-8 места.","H":{"I":"5abc9ccf494765f3cac7c6ad","T":"Россия (16)","XI":24857},"I":"5abc9cd3494765f3cac7fbc7","P":[{"A":15,"H":14,"T":18},{"A":19,"H":19,"T":19},{"A":16,"H":26,"T":20},{"A":14,"H":19,"T":21}],"S1":78,"S2":64,"SI":"5abc9cd3494765f3cac7fbb4","St":3,"T":"7-й матч","W":1},{"A":{"I":"5abc9ccf494765f3cac7c364","T":"Греция (16)","XI":24989},"D":1281812400,"H":{"I":"5abc9ccf494765f3cac7c5fc","T":"Италия (16)","XI":24839},"I":"5abc9cd3494765f3cac7fbf6","P":[{"A":16,"H":14,"T":18},{"A":11,"H":18,"T":19},{"A":11,"H":19,"T":20},{"A":15,"H":16,"T":21}],"S1":67,"S2":53,"SI":"5abc9cd3494765f3cac7fbe8","St":3,"T":"9-е место","W":1},{"A":{"I":"5abc9ccf494765f3cac7c66f","T":"Литва (16)","XI":24907},"D":1281812400,"H":{"I":"5abc9ccf494765f3cac7c664","T":"Турция (16)","XI":22265},"I":"5abc9cd5494765f3cac80883","P":[{"A":20,"H":12,"T":18},{"A":20,"H":13,"T":19},{"A":15,"H":14,"T":20},{"A":25,"H":26,"T":21}],"S1":65,"S2":80,"SI":"5abc9cd5494765f3cac80869","St":3,"T":"Полуфиналы","W":2},{"A":{"I":"5abc9cd3494765f3cac7fb18","T":"Болгария (16)","XI":24919},"D":1281804300,"H":{"I":"5abc9ccf494765f3cac7c35f","T":"Польша (16)","XI":24849},"I":"5abc9cd3494765f3cac7fbf7","P":[{"A":11,"H":20,"T":18},{"A":10,"H":17,"T":19},{"A":11,"H":17,"T":20},{"A":11,"H":14,"T":21}],"S1":68,"S2":43,"SI":"5abc9cd3494765f3cac7fbe8","St":3,"T":"11-е место","W":1},{"A":{"I":"5abc9ccf494765f3cac7c666","T":"Испания (16)","XI":24855},"D":1281804300,"H":{"I":"5abc9ccf494765f3cac7c66c","T":"Хорватия (16)","XI":24843},"I":"5abc9cd5494765f3cac8087f","P":[{"A":18,"H":22,"T":18},{"A":22,"H":15,"T":19},{"A":14,"H":18,"T":20},{"A":28,"H":31,"T":21}],"S1":86,"S2":82,"SI":"5abc9cd5494765f3cac80869","St":3,"T":"Полуфиналы","W":1}],"N":[{"I":"5ab11d10494765f3ca230666","T":"2018"},{"I":"5ab11d65494765f3ca2315c8","T":"2017"},{"I":"5ab11ddb494765f3ca232d74","T":"2016"},{"I":"5ab11e35494765f3ca235393","T":"2015"},{"I":"5ab11e85494765f3ca2367ff","T":"2014"},{"I":"5ab12632494765f3ca23fb68","T":"2013"},{"I":"5ab11d18494765f3ca23071a","T":"2012"},{"I":"5ab11d23494765f3ca230e27","T":"2011"},{"I":"5ab11d61494765f3ca231596","T":"2010"}],"S":[{"C":{"I":223,"T":"Европа"},"H":false,"I":"5abc9cd3494765f3cac7faf0","N":"ЕВРОПА: Евробаскет U16 - Предварительный раунд(Stat)","R":"5ab11d23494765f3ca230d91","T":2,"A":{"C":[{"R":[{"C":3,"D":0,"F":0,"G":[{"A":{"I":"5abc9ccf494765f3cac7c5fc","T":"Италия (16)","XI":24839},"D":1281199500,"H":{"I":"5abc9ccf494765f3cac7c56c","T":"Сербия (16)","XI":24909},"I":"5abc9cd3494765f3cac7fb2a","P":[{"A":15,"H":25,"T":18},{"A":12,"H":16,"T":19},{"A":26,"H":9,"T":20},{"A":8,"H":23,"T":21}],"R":1,"S1":73,"S2":61,"SI":"5abc9cd3494765f3cac7faf0","St":3,"W":1},{"A":{"I":"5abc9ccf494765f3cac7c56b","T":"Германия (16)","XI":24791},"D":1281113100,"H":{"I":"5abc9ccf494765f3cac7c56c","T":"Сербия (16)","XI":24909},"I":"5abc9cd3494765f3cac7fb44","P":[{"A":15,"H":17,"T":18},{"A":11,"H":20,"T":19},{"A":10,"H":17,"T":20},{"A":13,"H":24,"T":21}],"R":1,"S1":78,"S2":49,"SI":"5abc9cd3494765f3cac7faf0","St":3},{"A":{"I":"5abc9ccf494765f3cac7c56c","T":"Сербия (16)","XI":24909},"D":1281026700,"H":{"I":"5abc9ccf494765f3cac7c66c","T":"Хорватия (16)","XI":24843},"I":"5abc9cd3494765f3cac7fb0e","P":[{"A":6,"H":14,"T":18},{"A":23,"H":17,"T":19},{"A":20,"H":27,"T":20},{"A":15,"H":11,"T":21}],"R":2,"S1":69,"S2":64,"SI":"5abc9cd3494765f3cac7faf0","St":3,"W":1}],"L":1,"M":1,"N":"Проход дальше - Евробаскет U16(Stat)","P":5,"S":0,"T":{"I":"5abc9ccf494765f3cac7c56c","T":"Сербия (16)","XI":24909},"W":2},{"C":3,"D":0,"F":0,"G":[{"A":{"I":"5abc9ccf494765f3cac7c66c","T":"Хорватия (16)","XI":24843},"D":1281183300,"H":{"I":"5abc9ccf494765f3cac7c56b","T":"Германия (16)","XI":24791},"I":"5abc9cd3494765f3cac7fb0a","P":[{"A":21,"H":13,"T":18},{"A":7,"H":17,"T":19},{"A":6,"H":16,"T":20},{"A":10,"H":23,"T":21}],"R":2,"S1":69,"S2":44,"SI":"5abc9cd3494765f3cac7faf0","St":3},{"A":{"I":"5abc9ccf494765f3cac7c66c","T":"Хорватия (16)","XI":24843},"D":1281096900,"H":{"I":"5abc9ccf494765f3cac7c5fc","T":"Италия (16)","XI":24839},"I":"5abc9cd3494765f3cac7fb11","P":[{"A":17,"H":22,"T":18},{"A":16,"H":12,"T":19},{"A":22,"H":16,"T":20},{"A":17,"H":11,"T":21}],"R":1,"S1":61,"S2":72,"SI":"5abc9cd3494765f3cac7faf0","St":3},{"A":{"I":"5abc9ccf494765f3cac7c56c","T":"Сербия (16)","XI":24909},"D":1281026700,"H":{"I":"5abc9ccf494765f3cac7c66c","T":"Хорватия (16)","XI":24843},"I":"5abc9cd3494765f3cac7fb0e","P":[{"A":6,"H":14,"T":18},{"A":23,"H":17,"T":19},{"A":20,"H":27,"T":20},{"A":15,"H":11,"T":21}],"R":1,"S1":69,"S2":64,"SI":"5abc9cd3494765f3cac7faf0","St":3,"W":1}],"L":1,"M":2,"N":"Проход дальше - Евробаскет U16(Stat)","P":5,"S":0,"T":{"I":"5abc9ccf494765f3cac7c66c","T":"Хорватия (16)","XI":24843},"W":2},{"C":3,"D":0,"F":0,"G":[{"A":{"I":"5abc9ccf494765f3cac7c5fc","T":"Италия (16)","XI":24839},"D":1281199500,"H":{"I":"5abc9ccf494765f3cac7c56c","T":"Сербия (16)","XI":24909},"I":"5abc9cd3494765f3cac7fb2a","P":[{"A":15,"H":25,"T":18},{"A":12,"H":16,"T":19},{"A":26,"H":9,"T":20},{"A":8,"H":23,"T":21}],"R":2,"S1":73,"S2":61,"SI":"5abc9cd3494765f3cac7faf0","St":3,"W":1},{"A":{"I":"5abc9ccf494765f3cac7c66c","T":"Хорватия (16)","XI":24843},"D":1281096900,"H":{"I":"5abc9ccf494765f3cac7c5fc","T":"Италия (16)","XI":24839},"I":"5abc9cd3494765f3cac7fb11","P":[{"A":17,"H":22,"T":18},{"A":16,"H":12,"T":19},{"A":22,"H":16,"T":20},{"A":17,"H":11,"T":21}],"R":2,"S1":61,"S2":72,"SI":"5abc9cd3494765f3cac7faf0","St":3},{"A":{"I":"5abc9ccf494765f3cac7c5fc","T":"Италия (16)","XI":24839},"D":1281010500,"H":{"I":"5abc9ccf494765f3cac7c56b","T":"Германия (16)","XI":24791},"I":"5abc9cd3494765f3cac7fb95","P":[{"A":16,"H":21,"T":18},{"A":25,"H":9,"T":19},{"A":13,"H":16,"T":20},{"A":19,"H":8,"T":21}],"R":1,"S1":54,"S2":73,"SI":"5abc9cd3494765f3cac7faf0","St":3,"W":2}],"L":2,"M":3,"N":"Проход дальше - Евробаскет U16(Stat)","P":4,"S":0,"T":{"I":"5abc9ccf494765f3cac7c5fc","T":"Италия (16)","XI":24839},"W":1},{"C":3,"D":0,"F":0,"G":[{"A":{"I":"5abc9ccf494765f3cac7c66c","T":"Хорватия (16)","XI":24843},"D":1281183300,"H":{"I":"5abc9ccf494765f3cac7c56b","T":"Германия (16)","XI":24791},"I":"5abc9cd3494765f3cac7fb0a","P":[{"A":21,"H":13,"T":18},{"A":7,"H":17,"T":19},{"A":6,"H":16,"T":20},{"A":10,"H":23,"T":21}],"R":1,"S1":69,"S2":44,"SI":"5abc9cd3494765f3cac7faf0","St":3},{"A":{"I":"5abc9ccf494765f3cac7c56b","T":"Германия (16)","XI":24791},"D":1281113100,"H":{"I":"5abc9ccf494765f3cac7c56c","T":"Сербия (16)","XI":24909},"I":"5abc9cd3494765f3cac7fb44","P":[{"A":15,"H":17,"T":18},{"A":11,"H":20,"T":19},{"A":10,"H":17,"T":20},{"A":13,"H":24,"T":21}],"R":2,"S1":78,"S2":49,"SI":"5abc9cd3494765f3cac7faf0","St":3},{"A":{"I":"5abc9ccf494765f3cac7c5fc","T":"Италия (16)","XI":24839},"D":1281010500,"H":{"I":"5abc9ccf494765f3cac7c56b","T":"Германия (16)","XI":24791},"I":"5abc9cd3494765f3cac7fb95","P":[{"A":16,"H":21,"T":18},{"A":25,"H":9,"T":19},{"A":13,"H":16,"T":20},{"A":19,"H":8,"T":21}],"R":2,"S1":54,"S2":73,"SI":"5abc9cd3494765f3cac7faf0","St":3,"W":2}],"L":2,"M":4,"N":"Евробаскет U16 (13-16 места)(Stat)","P":4,"S":0,"T":{"I":"5abc9ccf494765f3cac7c56b","T":"Германия (16)","XI":24791},"W":1}],"T":"Группа A"},{"R":[{"C":3,"D":0,"F":0,"G":[{"A":{"I":"5abc9ccf494765f3cac7c605","T":"Франция (16)","XI":24911},"D":1281199500,"H":{"I":"5abc9cd1494765f3cac7d9cb","T":"Дания (16)","XI":25579},"I":"5abc9cd3494765f3cac7fb2f","P":[{"A":22,"H":14,"T":18},{"A":18,"H":14,"T":19},{"A":16,"H":6,"T":20},{"A":17,"H":1,"T":21}],"R":1,"S1":35,"S2":73,"SI":"5abc9cd3494765f3cac7faf0","St":3,"W":2},{"A":{"I":"5abc9ccf494765f3cac7c605","T":"Франция (16)","XI":24911},"D":1281121200,"H":{"I":"5abc9ccf494765f3cac7c364","T":"Греция (16)","XI":24989},"I":"5abc9cd3494765f3cac7fb7b","P":[{"A":9,"H":15,"T":18},{"A":8,"H":11,"T":19},{"A":20,"H":18,"T":20},{"A":18,"H":8,"T":21}],"R":1,"S1":52,"S2":55,"SI":"5abc9cd3494765f3cac7faf0","St":3,"W":2},{"A":{"I":"5abc9ccf494765f3cac7c66f","T":"Литва (16)","XI":24907},"D":1281034800,"H":{"I":"5abc9ccf494765f3cac7c605","T":"Франция (16)","XI":24911},"I":"5abc9cd3494765f3cac7fb50","P":[{"A":14,"H":22,"T":18},{"A":14,"H":15,"T":19},{"A":10,"H":11,"T":20},{"A":8,"H":18,"T":21}],"R":1,"S1":66,"S2":46,"SI":"5abc9cd3494765f3cac7faf0","St":3,"W":1}],"L":0,"M":1,"N":"Проход дальше - Евробаскет U16(Stat)","P":6,"S":0,"T":{"I":"5abc9ccf494765f3cac7c605","T":"Франция (16)","XI":24911},"W":3},{"C":3,"D":0,"F":0,"G":[{"A":{"I":"5abc9ccf494765f3cac7c364","T":"Греция (16)","XI":24989},"D":1281207600,"H":{"I":"5abc9ccf494765f3cac7c66f","T":"Литва (16)","XI":24907},"I":"5abc9cd3494765f3cac7fb0f","P":[{"A":14,"H":17,"T":18},{"A":15,"H":15,"T":19},{"A":16,"H":13,"T":20},{"A":21,"H":18,"T":21}],"R":2,"S1":63,"S2":66,"SI":"5abc9cd3494765f3cac7faf0","St":3,"W":2},{"A":{"I":"5abc9cd1494765f3cac7d9cb","T":"Дания (16)","XI":25579},"D":1281113100,"H":{"I":"5abc9ccf494765f3cac7c66f","T":"Литва (16)","XI":24907},"I":"5abc9cd3494765f3cac7fb43","P":[{"A":5,"H":32,"T":18},{"A":11,"H":21,"T":19},{"A":9,"H":24,"T":20},{"A":22,"H":15,"T":21}],"R":1,"S1":92,"S2":47,"SI":"5abc9cd3494765f3cac7faf0","St":3,"W":1},{"A":{"I":"5abc9ccf494765f3cac7c66f","T":"Литва (16)","XI":24907},"D":1281034800,"H":{"I":"5abc9ccf494765f3cac7c605","T":"Франция (16)","XI":24911},"I":"5abc9cd3494765f3cac7fb50","P":[{"A":14,"H":22,"T":18},{"A":14,"H":15,"T":19},{"A":10,"H":11,"T":20},{"A":8,"H":18,"T":21}],"R":2,"S1":66,"S2":46,"SI":"5abc9cd3494765f3cac7faf0","St":3,"W":1}],"L":2,"M":2,"N":"Проход дальше - Евробаскет U16(Stat)","P":4,"S":0,"T":{"I":"5abc9ccf494765f3cac7c66f","T":"Литва (16)","XI":24907},"W":1},{"C":3,"D":0,"F":0,"G":[{"A":{"I":"5abc9ccf494765f3cac7c364","T":"Греция (16)","XI":24989},"D":1281207600,"H":{"I":"5abc9ccf494765f3cac7c66f","T":"Литва (16)","XI":24907},"I":"5abc9cd3494765f3cac7fb0f","P":[{"A":14,"H":17,"T":18},{"A":15,"H":15,"T":19},{"A":16,"H":13,"T":20},{"A":21,"H":18,"T":21}],"R":1,"S1":63,"S2":66,"SI":"5abc9cd3494765f3cac7faf0","St":3,"W":2},{"A":{"I":"5abc9ccf494765f3cac7c605","T":"Франция (16)","XI":24911},"D":1281121200,"H":{"I":"5abc9ccf494765f3cac7c364","T":"Греция (16)","XI":24989},"I":"5abc9cd3494765f3cac7fb7b","P":[{"A":9,"H":15,"T":18},{"A":8,"H":11,"T":19},{"A":20,"H":18,"T":20},{"A":18,"H":8,"T":21}],"R":2,"S1":52,"S2":55,"SI":"5abc9cd3494765f3cac7faf0","St":3,"W":2},{"A":{"I":"5abc9ccf494765f3cac7c364","T":"Греция (16)","XI":24989},"D":1281026700,"H":{"I":"5abc9cd1494765f3cac7d9cb","T":"Дания (16)","XI":25579},"I":"5abc9cd3494765f3cac7fb0d","P":[{"A":11,"H":9,"T":18},{"A":17,"H":16,"T":19},{"A":11,"H":19,"T":20},{"A":14,"H":11,"T":21}],"R":2,"S1":55,"S2":53,"SI":"5abc9cd3494765f3cac7faf0","St":3,"W":1}],"L":2,"M":3,"N":"Проход дальше - Евробаскет U16(Stat)","P":4,"S":0,"T":{"I":"5abc9ccf494765f3cac7c364","T":"Греция (16)","XI":24989},"W":1},{"C":3,"D":0,"F":0,"G":[{"A":{"I":"5abc9ccf494765f3cac7c605","T":"Франция (16)","XI":24911},"D":1281199500,"H":{"I":"5abc9cd1494765f3cac7d9cb","T":"Дания (16)","XI":25579},"I":"5abc9cd3494765f3cac7fb2f","P":[{"A":22,"H":14,"T":18},{"A":18,"H":14,"T":19},{"A":16,"H":6,"T":20},{"A":17,"H":1,"T":21}],"R":2,"S1":35,"S2":73,"SI":"5abc9cd3494765f3cac7faf0","St":3,"W":2},{"A":{"I":"5abc9cd1494765f3cac7d9cb","T":"Дания (16)","XI":25579},"D":1281113100,"H":{"I":"5abc9ccf494765f3cac7c66f","T":"Литва (16)","XI":24907},"I":"5abc9cd3494765f3cac7fb43","P":[{"A":5,"H":32,"T":18},{"A":11,"H":21,"T":19},{"A":9,"H":24,"T":20},{"A":22,"H":15,"T":21}],"R":2,"S1":92,"S2":47,"SI":"5abc9cd3494765f3cac7faf0","St":3,"W":1},{"A":{"I":"5abc9ccf494765f3cac7c364","T":"Греция (16)","XI":24989},"D":1281026700,"H":{"I":"5abc9cd1494765f3cac7d9cb","T":"Дания (16)","XI":25579},"I":"5abc9cd3494765f3cac7fb0d","P":[{"A":11,"H":9,"T":18},{"A":17,"H":16,"T":19},{"A":11,"H":19,"T":20},{"A":14,"H":11,"T":21}],"R":1,"S1":55,"S2":53,"SI":"5abc9cd3494765f3cac7faf0","St":3,"W":1}],"L":2,"M":4,"N":"Евробаскет U16 (13-16 места)(Stat)","P":4,"S":0,"T":{"I":"5abc9cd1494765f3cac7d9cb","T":"Дания (16)","XI":25579},"W":1}],"T":"Группа B"},{"R":[{"C":3,"D":0,"F":0,"G":[{"A":{"I":"5abc9ccf494765f3cac7c35f","T":"Польша (16)","XI":24849},"D":1281191400,"H":{"I":"5abc9ccf494765f3cac7c666","T":"Испания (16)","XI":24855},"I":"5abc9cd3494765f3cac7fb09","P":[{"A":17,"H":21,"T":18},{"A":16,"H":15,"T":19},{"A":10,"H":23,"T":20},{"A":9,"H":17,"T":21}],"R":1,"S1":76,"S2":52,"SI":"5abc9cd3494765f3cac7faf0","St":3,"W":1},{"A":{"I":"5abc9cd3494765f3cac7fb18","T":"Болгария (16)","XI":24919},"D":1281105000,"H":{"I":"5abc9ccf494765f3cac7c666","T":"Испания (16)","XI":24855},"I":"5abc9cd3494765f3cac7fb36","P":[{"A":9,"H":14,"T":18},{"A":13,"H":20,"T":19},{"A":12,"H":31,"T":20},{"A":6,"H":14,"T":21}],"R":1,"S1":79,"S2":40,"SI":"5abc9cd3494765f3cac7faf0","St":3,"W":1},{"A":{"I":"5abc9ccf494765f3cac7c666","T":"Испания (16)","XI":24855},"D":1281018600,"H":{"I":"5abc9ccf494765f3cac7c569","T":"Латвия (16)","XI":22263},"I":"5abc9cd3494765f3cac7fb27","P":[{"A":16,"H":4,"T":18},{"A":23,"H":14,"T":19},{"A":17,"H":7,"T":20},{"A":9,"H":7,"T":21}],"R":1,"S1":32,"S2":65,"SI":"5abc9cd3494765f3cac7faf0","St":3}],"L":0,"M":1,"N":"Проход дальше - Евробаскет U16(Stat)","P":6,"S":0,"T":{"I":"5abc9ccf494765f3cac7c666","T":"Испания (16)","XI":24855},"W":3},{"C":3,"D":0,"F":0,"G":[{"A":{"I":"5abc9ccf494765f3cac7c569","T":"Латвия (16)","XI":22263},"D":1281183300,"H":{"I":"5abc9cd3494765f3cac7fb18","T":"Болгария (16)","XI":24919},"I":"5abc9cd3494765f3cac7fb2d","P":[{"A":12,"H":17,"T":18},{"A":13,"H":14,"T":19},{"A":19,"H":20,"T":20},{"A":22,"H":18,"T":21}],"R":1,"S1":69,"S2":66,"SI":"5abc9cd3494765f3cac7faf0","St":3,"W":1},{"A":{"I":"5abc9cd3494765f3cac7fb18","T":"Болгария (16)","XI":24919},"D":1281105000,"H":{"I":"5abc9ccf494765f3cac7c666","T":"Испания (16)","XI":24855},"I":"5abc9cd3494765f3cac7fb36","P":[{"A":9,"H":14,"T":18},{"A":13,"H":20,"T":19},{"A":12,"H":31,"T":20},{"A":6,"H":14,"T":21}],"R":2,"S1":79,"S2":40,"SI":"5abc9cd3494765f3cac7faf0","St":3,"W":1},{"A":{"I":"5abc9ccf494765f3cac7c35f","T":"Польша (16)","XI":24849},"D":1281010500,"H":{"I":"5abc9cd3494765f3cac7fb18","T":"Болгария (16)","XI":24919},"I":"5abc9cd3494765f3cac7fb8b","P":[{"A":12,"H":5,"T":18},{"A":15,"H":24,"T":19},{"A":11,"H":24,"T":20},{"A":15,"H":26,"T":21}],"R":1,"S1":79,"S2":53,"SI":"5abc9cd3494765f3cac7faf0","St":3,"W":1}],"L":1,"M":2,"N":"Проход дальше - Евробаскет U16(Stat)","P":5,"S":0,"T":{"I":"5abc9cd3494765f3cac7fb18","T":"Болгария (16)","XI":24919},"W":2},{"C":3,"D":0,"F":0,"G":[{"A":{"I":"5abc9ccf494765f3cac7c35f","T":"Польша (16)","XI":24849},"D":1281191400,"H":{"I":"5abc9ccf494765f3cac7c666","T":"Испания (16)","XI":24855},"I":"5abc9cd3494765f3cac7fb09","P":[{"A":17,"H":21,"T":18},{"A":16,"H":15,"T":19},{"A":10,"H":23,"T":20},{"A":9,"H":17,"T":21}],"R":2,"S1":76,"S2":52,"SI":"5abc9cd3494765f3cac7faf0","St":3,"W":1},{"A":{"I":"5abc9ccf494765f3cac7c569","T":"Латвия (16)","XI":22263},"D":1281096900,"H":{"I":"5abc9ccf494765f3cac7c35f","T":"Польша (16)","XI":24849},"I":"5abc9cd3494765f3cac7fb40","P":[{"A":10,"H":26,"T":18},{"A":15,"H":12,"T":19},{"A":13,"H":20,"T":20},{"A":7,"H":14,"T":21}],"R":1,"S1":72,"S2":45,"SI":"5abc9cd3494765f3cac7faf0","St":3,"W":1},{"A":{"I":"5abc9ccf494765f3cac7c35f","T":"Польша (16)","XI":24849},"D":1281010500,"H":{"I":"5abc9cd3494765f3cac7fb18","T":"Болгария (16)","XI":24919},"I":"5abc9cd3494765f3cac7fb8b","P":[{"A":12,"H":5,"T":18},{"A":15,"H":24,"T":19},{"A":11,"H":24,"T":20},{"A":15,"H":26,"T":21}],"R":2,"S1":79,"S2":53,"SI":"5abc9cd3494765f3cac7faf0","St":3,"W":1}],"L":2,"M":3,"N":"Проход дальше - Евробаскет U16(Stat)","P":4,"S":0,"T":{"I":"5abc9ccf494765f3cac7c35f","T":"Польша (16)","XI":24849},"W":1},{"C":3,"D":0,"F":0,"G":[{"A":{"I":"5abc9ccf494765f3cac7c569","T":"Латвия (16)","XI":22263},"D":1281183300,"H":{"I":"5abc9cd3494765f3cac7fb18","T":"Болгария (16)","XI":24919},"I":"5abc9cd3494765f3cac7fb2d","P":[{"A":12,"H":17,"T":18},{"A":13,"H":14,"T":19},{"A":19,"H":20,"T":20},{"A":22,"H":18,"T":21}],"R":2,"S1":69,"S2":66,"SI":"5abc9cd3494765f3cac7faf0","St":3,"W":1},{"A":{"I":"5abc9ccf494765f3cac7c569","T":"Латвия (16)","XI":22263},"D":1281096900,"H":{"I":"5abc9ccf494765f3cac7c35f","T":"Польша (16)","XI":24849},"I":"5abc9cd3494765f3cac7fb40","P":[{"A":10,"H":26,"T":18},{"A":15,"H":12,"T":19},{"A":13,"H":20,"T":20},{"A":7,"H":14,"T":21}],"R":2,"S1":72,"S2":45,"SI":"5abc9cd3494765f3cac7faf0","St":3,"W":1},{"A":{"I":"5abc9ccf494765f3cac7c666","T":"Испания (16)","XI":24855},"D":1281018600,"H":{"I":"5abc9ccf494765f3cac7c569","T":"Латвия (16)","XI":22263},"I":"5abc9cd3494765f3cac7fb27","P":[{"A":16,"H":4,"T":18},{"A":23,"H":14,"T":19},{"A":17,"H":7,"T":20},{"A":9,"H":7,"T":21}],"R":2,"S1":32,"S2":65,"SI":"5abc9cd3494765f3cac7faf0","St":3}],"L":3,"M":4,"N":"Евробаскет U16 (13-16 места)(Stat)","P":3,"S":0,"T":{"I":"5abc9ccf494765f3cac7c569","T":"Латвия (16)","XI":22263},"W":0}],"T":"Группа C"},{"R":[{"C":3,"D":0,"F":0,"G":[{"A":{"I":"5abc9ccf494765f3cac7c6ad","T":"Россия (16)","XI":24857},"D":1281207600,"H":{"I":"5abc9ccf494765f3cac7c5fd","T":"Черногория (16)","XI":24847},"I":"5abc9cd3494765f3cac7fb13","P":[{"A":16,"H":14,"T":18},{"A":25,"H":19,"T":19},{"A":10,"H":13,"T":20},{"A":9,"H":19,"T":21}],"R":1,"S1":65,"S2":60,"SI":"5abc9cd3494765f3cac7faf0","St":3,"W":1},{"A":{"I":"5abc9ccf494765f3cac7c5fd","T":"Черногория (16)","XI":24847},"D":1281121200,"H":{"I":"5abc9ccf494765f3cac7c664","T":"Турция (16)","XI":22265},"I":"5abc9cd3494765f3cac7fb3f","P":[{"A":17,"H":8,"T":18},{"A":17,"H":19,"T":19},{"A":15,"H":11,"T":20},{"A":18,"H":16,"T":21}],"R":1,"S1":54,"S2":67,"SI":"5abc9cd3494765f3cac7faf0","St":3,"W":2},{"A":{"I":"5abc9ccf494765f3cac7c6ae","T":"Израиль (16)","XI":25015},"D":1281034800,"H":{"I":"5abc9ccf494765f3cac7c5fd","T":"Черногория (16)","XI":24847},"I":"5abc9cd3494765f3cac7fb2c","P":[{"A":13,"H":19,"T":18},{"A":9,"H":23,"T":19},{"A":22,"H":19,"T":20},{"A":27,"H":20,"T":21}],"R":1,"S1":81,"S2":71,"SI":"5abc9cd3494765f3cac7faf0","St":3}],"L":0,"M":1,"N":"Проход дальше - Евробаскет U16(Stat)","P":6,"S":0,"T":{"I":"5abc9ccf494765f3cac7c5fd","T":"Черногория (16)","XI":24847},"W":3},{"C":3,"D":0,"F":0,"G":[{"A":{"I":"5abc9ccf494765f3cac7c6ae","T":"Израиль (16)","XI":25015},"D":1281191400,"H":{"I":"5abc9ccf494765f3cac7c664","T":"Турция (16)","XI":22265},"I":"5abc9cd3494765f3cac7fb77","P":[{"A":5,"H":6,"T":18},{"A":13,"H":16,"T":19},{"A":16,"H":20,"T":20},{"A":27,"H":16,"T":21}],"R":2,"S1":58,"S2":61,"SI":"5abc9cd3494765f3cac7faf0","St":3,"W":2},{"A":{"I":"5abc9ccf494765f3cac7c5fd","T":"Черногория (16)","XI":24847},"D":1281121200,"H":{"I":"5abc9ccf494765f3cac7c664","T":"Турция (16)","XI":22265},"I":"5abc9cd3494765f3cac7fb3f","P":[{"A":17,"H":8,"T":18},{"A":17,"H":19,"T":19},{"A":15,"H":11,"T":20},{"A":18,"H":16,"T":21}],"R":2,"S1":54,"S2":67,"SI":"5abc9cd3494765f3cac7faf0","St":3,"W":2},{"A":{"I":"5abc9ccf494765f3cac7c664","T":"Турция (16)","XI":22265},"D":1281018600,"H":{"I":"5abc9ccf494765f3cac7c6ad","T":"Россия (16)","XI":24857},"I":"5abc9cd3494765f3cac7fb29","P":[{"A":13,"H":17,"T":18},{"A":24,"H":14,"T":19},{"A":17,"H":7,"T":20},{"A":17,"H":12,"T":21}],"R":1,"S1":50,"S2":71,"SI":"5abc9cd3494765f3cac7faf0","St":3,"W":2}],"L":2,"M":2,"N":"Проход дальше - Евробаскет U16(Stat)","P":4,"S":0,"T":{"I":"5abc9ccf494765f3cac7c664","T":"Турция (16)","XI":22265},"W":1},{"C":3,"D":0,"F":0,"G":[{"A":{"I":"5abc9ccf494765f3cac7c6ad","T":"Россия (16)","XI":24857},"D":1281207600,"H":{"I":"5abc9ccf494765f3cac7c5fd","T":"Черногория (16)","XI":24847},"I":"5abc9cd3494765f3cac7fb13","P":[{"A":16,"H":14,"T":18},{"A":25,"H":19,"T":19},{"A":10,"H":13,"T":20},{"A":9,"H":19,"T":21}],"R":2,"S1":65,"S2":60,"SI":"5abc9cd3494765f3cac7faf0","St":3,"W":1},{"A":{"I":"5abc9ccf494765f3cac7c6ad","T":"Россия (16)","XI":24857},"D":1281105000,"H":{"I":"5abc9ccf494765f3cac7c6ae","T":"Израиль (16)","XI":25015},"I":"5abc9cd3494765f3cac7fb0c","P":[{"A":22,"H":7,"T":18},{"A":17,"H":15,"T":19},{"A":17,"H":16,"T":20},{"A":20,"H":20,"T":21}],"R":1,"S1":58,"S2":76,"SI":"5abc9cd3494765f3cac7faf0","St":3,"W":2},{"A":{"I":"5abc9ccf494765f3cac7c664","T":"Турция (16)","XI":22265},"D":1281018600,"H":{"I":"5abc9ccf494765f3cac7c6ad","T":"Россия (16)","XI":24857},"I":"5abc9cd3494765f3cac7fb29","P":[{"A":13,"H":17,"T":18},{"A":24,"H":14,"T":19},{"A":17,"H":7,"T":20},{"A":17,"H":12,"T":21}],"R":2,"S1":50,"S2":71,"SI":"5abc9cd3494765f3cac7faf0","St":3,"W":2}],"L":2,"M":3,"N":"Проход дальше - Евробаскет U16(Stat)","P":4,"S":0,"T":{"I":"5abc9ccf494765f3cac7c6ad","T":"Россия (16)","XI":24857},"W":1},{"C":3,"D":0,"F":0,"G":[{"A":{"I":"5abc9ccf494765f3cac7c6ae","T":"Израиль (16)","XI":25015},"D":1281191400,"H":{"I":"5abc9ccf494765f3cac7c664","T":"Турция (16)","XI":22265},"I":"5abc9cd3494765f3cac7fb77","P":[{"A":5,"H":6,"T":18},{"A":13,"H":16,"T":19},{"A":16,"H":20,"T":20},{"A":27,"H":16,"T":21}],"R":1,"S1":58,"S2":61,"SI":"5abc9cd3494765f3cac7faf0","St":3,"W":2},{"A":{"I":"5abc9ccf494765f3cac7c6ad","T":"Россия (16)","XI":24857},"D":1281105000,"H":{"I":"5abc9ccf494765f3cac7c6ae","T":"Израиль (16)","XI":25015},"I":"5abc9cd3494765f3cac7fb0c","P":[{"A":22,"H":7,"T":18},{"A":17,"H":15,"T":19},{"A":17,"H":16,"T":20},{"A":20,"H":20,"T":21}],"R":2,"S1":58,"S2":76,"SI":"5abc9cd3494765f3cac7faf0","St":3,"W":2},{"A":{"I":"5abc9ccf494765f3cac7c6ae","T":"Израиль (16)","XI":25015},"D":1281034800,"H":{"I":"5abc9ccf494765f3cac7c5fd","T":"Черногория (16)","XI":24847},"I":"5abc9cd3494765f3cac7fb2c","P":[{"A":13,"H":19,"T":18},{"A":9,"H":23,"T":19},{"A":22,"H":19,"T":20},{"A":27,"H":20,"T":21}],"R":2,"S1":81,"S2":71,"SI":"5abc9cd3494765f3cac7faf0","St":3}],"L":2,"M":4,"N":"Евробаскет U16 (13-16 места)(Stat)","P":4,"S":0,"T":{"I":"5abc9ccf494765f3cac7c6ae","T":"Израиль (16)","XI":25015},"W":1}],"T":"Группа D"}]}},{"C":{"I":223,"T":"Европа"},"H":false,"I":"5abc9cd3494765f3cac7fbe8","N":"ЕВРОПА: Евробаскет U16 - 9-12 места(Stat)","R":"5ab11d23494765f3ca230d91","T":1,"D":{"C":[{"A":{"I":"5abc9ccf494765f3cac7c364","T":"Греция (16)","XI":24989},"C":{"A":{"I":"5abc9ccf494765f3cac7c35f","T":"Польша (16)","XI":24849},"G":[{"A":{"I":"5abc9ccf494765f3cac7c35f","T":"Польша (16)","XI":24849},"D":1281717900,"H":{"I":"5abc9ccf494765f3cac7c5fc","T":"Италия (16)","XI":24839},"I":"5abc9cd3494765f3cac7fbf8","P":[{"A":23,"H":18,"T":18},{"A":23,"H":22,"T":19},{"A":4,"H":17,"T":20},{"A":11,"H":19,"T":21}],"S1":76,"S2":61,"SI":"5abc9cd3494765f3cac7fbe8","St":3,"T":"Полуфиналы","W":1}],"H":{"I":"5abc9ccf494765f3cac7c5fc","T":"Италия (16)","XI":24839},"T":"Полуфиналы"},"D":{"A":{"I":"5abc9ccf494765f3cac7c364","T":"Греция (16)","XI":24989},"G":[{"A":{"I":"5abc9ccf494765f3cac7c364","T":"Греция (16)","XI":24989},"D":1281726000,"H":{"I":"5abc9cd3494765f3cac7fb18","T":"Болгария (16)","XI":24919},"I":"5abc9cd3494765f3cac7fbf5","P":[{"A":18,"H":10,"T":18},{"A":15,"H":18,"T":19},{"A":25,"H":10,"T":20},{"A":20,"H":29,"T":21}],"S1":67,"S2":78,"SI":"5abc9cd3494765f3cac7fbe8","St":3,"T":"Полуфиналы","W":2}],"H":{"I":"5abc9cd3494765f3cac7fb18","T":"Болгария (16)","XI":24919},"T":"Полуфиналы"},"G":[{"A":{"I":"5abc9ccf494765f3cac7c364","T":"Греция (16)","XI":24989},"D":1281812400,"H":{"I":"5abc9ccf494765f3cac7c5fc","T":"Италия (16)","XI":24839},"I":"5abc9cd3494765f3cac7fbf6","P":[{"A":16,"H":14,"T":18},{"A":11,"H":18,"T":19},{"A":11,"H":19,"T":20},{"A":15,"H":16,"T":21}],"S1":67,"S2":53,"SI":"5abc9cd3494765f3cac7fbe8","St":3,"T":"9-е место","W":1}],"H":{"I":"5abc9ccf494765f3cac7c5fc","T":"Италия (16)","XI":24839},"T":"9-е место"},{"A":{"I":"5abc9cd3494765f3cac7fb18","T":"Болгария (16)","XI":24919},"G":[{"A":{"I":"5abc9cd3494765f3cac7fb18","T":"Болгария (16)","XI":24919},"D":1281804300,"H":{"I":"5abc9ccf494765f3cac7c35f","T":"Польша (16)","XI":24849},"I":"5abc9cd3494765f3cac7fbf7","P":[{"A":11,"H":20,"T":18},{"A":10,"H":17,"T":19},{"A":11,"H":17,"T":20},{"A":11,"H":14,"T":21}],"S1":68,"S2":43,"SI":"5abc9cd3494765f3cac7fbe8","St":3,"T":"11-е место","W":1}],"H":{"I":"5abc9ccf494765f3cac7c35f","T":"Польша (16)","XI":24849},"T":"11-е место"}]}},{"C":{"I":223,"T":"Европа"},"H":false,"I":"5abc9cd3494765f3cac7fbb4","N":"ЕВРОПА: Евробаскет U16 - 5-8 места(Stat)","R":"5ab11d23494765f3ca230d91","T":1,"D":{"C":[{"A":{"I":"5abc9ccf494765f3cac7c56c","T":"Сербия (16)","XI":24909},"C":{"A":{"I":"5abc9ccf494765f3cac7c605","T":"Франция (16)","XI":24911},"G":[{"A":{"I":"5abc9ccf494765f3cac7c605","T":"Франция (16)","XI":24911},"D":1281788100,"H":{"I":"5abc9ccf494765f3cac7c6ad","T":"Россия (16)","XI":24857},"I":"5abc9cd3494765f3cac7fbc8","P":[{"A":22,"H":16,"T":18},{"A":11,"H":9,"T":19},{"A":16,"H":15,"T":20},{"A":19,"H":11,"T":21}],"S1":51,"S2":68,"SI":"5abc9cd3494765f3cac7fbb4","St":3}],"H":{"I":"5abc9ccf494765f3cac7c6ad","T":"Россия (16)","XI":24857},"T":"Полуфиналы"},"D":{"A":{"I":"5abc9ccf494765f3cac7c5fd","T":"Черногория (16)","XI":24847},"G":[{"A":{"I":"5abc9ccf494765f3cac7c5fd","T":"Черногория (16)","XI":24847},"D":1281796200,"DI":"За 5-8 места.","H":{"I":"5abc9ccf494765f3cac7c56c","T":"Сербия (16)","XI":24909},"I":"5abc9cd3494765f3cac7fbc4","P":[{"A":18,"H":24,"T":18},{"A":22,"H":14,"T":19},{"A":16,"H":23,"T":20},{"A":18,"H":17,"T":21}],"S1":78,"S2":74,"SI":"5abc9cd3494765f3cac7fbb4","St":3,"T":"Полуфиналы","W":1}],"H":{"I":"5abc9ccf494765f3cac7c56c","T":"Сербия (16)","XI":24909},"T":"Полуфиналы"},"G":[{"A":{"I":"5abc9ccf494765f3cac7c56c","T":"Сербия (16)","XI":24909},"D":1281871800,"DI":"За 5-6 места.","H":{"I":"5abc9ccf494765f3cac7c605","T":"Франция (16)","XI":24911},"I":"5abc9cd3494765f3cac7fbc5","P":[{"A":17,"H":10,"T":18},{"A":15,"H":9,"T":19},{"A":13,"H":14,"T":20},{"A":10,"H":12,"T":21}],"S1":45,"S2":55,"SI":"5abc9cd3494765f3cac7fbb4","St":3,"T":"5-е место","W":2}],"H":{"I":"5abc9ccf494765f3cac7c605","T":"Франция (16)","XI":24911},"T":"5-е место"},{"A":{"I":"5abc9ccf494765f3cac7c5fd","T":"Черногория (16)","XI":24847},"G":[{"A":{"I":"5abc9ccf494765f3cac7c5fd","T":"Черногория (16)","XI":24847},"D":1281863700,"DI":"За 7-8 места.","H":{"I":"5abc9ccf494765f3cac7c6ad","T":"Россия (16)","XI":24857},"I":"5abc9cd3494765f3cac7fbc7","P":[{"A":15,"H":14,"T":18},{"A":19,"H":19,"T":19},{"A":16,"H":26,"T":20},{"A":14,"H":19,"T":21}],"S1":78,"S2":64,"SI":"5abc9cd3494765f3cac7fbb4","St":3,"T":"7-й матч","W":1}],"H":{"I":"5abc9ccf494765f3cac7c6ad","T":"Россия (16)","XI":24857},"T":"7-й матч"}]}},{"C":{"I":223,"T":"Европа"},"H":false,"I":"5abc9cd3494765f3cac7fc38","N":"ЕВРОПА: Евробаскет U16 - 13-16 места(Stat)","R":"5ab11d23494765f3ca230d91","T":2,"A":{"C":[{"R":[{"C":6,"D":0,"F":0,"G":[{"A":{"I":"5abc9ccf494765f3cac7c56b","T":"Германия (16)","XI":24791},"D":1281874500,"H":{"I":"5abc9cd1494765f3cac7d9cb","T":"Дания (16)","XI":25579},"I":"5abc9cd4494765f3cac7fc50","P":[{"A":18,"H":24,"T":18},{"A":17,"H":21,"T":19},{"A":18,"H":12,"T":20},{"A":19,"H":20,"T":21}],"R":2,"S1":77,"S2":72,"SI":"5abc9cd3494765f3cac7fc38","St":3,"W":1},{"A":{"I":"5abc9ccf494765f3cac7c569","T":"Латвия (16)","XI":22263},"D":1281796200,"H":{"I":"5abc9ccf494765f3cac7c56b","T":"Германия (16)","XI":24791},"I":"5abc9cd4494765f3cac7fc52","P":[{"A":14,"H":19,"T":18},{"A":14,"H":15,"T":19},{"A":2,"H":13,"T":20},{"A":16,"H":16,"T":21}],"R":1,"S1":63,"S2":46,"SI":"5abc9cd3494765f3cac7fc38","St":3,"W":1},{"A":{"I":"5abc9ccf494765f3cac7c56b","T":"Германия (16)","XI":24791},"D":1281701700,"H":{"I":"5abc9ccf494765f3cac7c6ae","T":"Израиль (16)","XI":25015},"I":"5abc9cd4494765f3cac7fc99","P":[{"A":12,"H":11,"T":18},{"A":13,"H":17,"T":19},{"A":13,"H":12,"T":20},{"A":11,"H":20,"T":21}],"R":2,"S1":60,"S2":49,"SI":"5abc9cd3494765f3cac7fc38","St":3,"W":1},{"A":{"I":"5abc9cd1494765f3cac7d9cb","T":"Дания (16)","XI":25579},"D":1281528900,"H":{"I":"5abc9ccf494765f3cac7c56b","T":"Германия (16)","XI":24791},"I":"5abc9cd4494765f3cac7fc54","P":[{"A":7,"H":24,"T":18},{"A":13,"H":17,"T":19},{"A":11,"H":13,"T":20},{"A":9,"H":14,"T":21}],"R":1,"S1":68,"S2":40,"SI":"5abc9cd3494765f3cac7fc38","St":3,"W":1},{"A":{"I":"5abc9ccf494765f3cac7c56b","T":"Германия (16)","XI":24791},"D":1281442500,"H":{"I":"5abc9ccf494765f3cac7c569","T":"Латвия (16)","XI":22263},"I":"5abc9cd4494765f3cac7fc57","P":[{"A":19,"H":16,"T":18},{"A":11,"H":14,"T":19},{"A":14,"H":7,"T":20},{"A":12,"H":17,"T":21}],"R":1,"S1":54,"S2":56,"SI":"5abc9cd3494765f3cac7fc38","St":3,"W":2}],"L":2,"M":1,"P":10,"S":0,"T":{"I":"5abc9ccf494765f3cac7c56b","T":"Германия (16)","XI":24791},"W":4},{"C":6,"D":0,"F":0,"G":[{"A":{"I":"5abc9ccf494765f3cac7c569","T":"Латвия (16)","XI":22263},"D":1281882600,"H":{"I":"5abc9ccf494765f3cac7c6ae","T":"Израиль (16)","XI":25015},"I":"5abc9cd4494765f3cac7fcc4","P":[{"A":15,"H":17,"T":18},{"A":18,"H":11,"T":19},{"A":14,"H":12,"T":20},{"A":18,"H":22,"T":21}],"R":1,"S1":62,"S2":65,"SI":"5abc9cd3494765f3cac7fc38","St":3},{"A":{"I":"5abc9ccf494765f3cac7c569","T":"Латвия (16)","XI":22263},"D":1281796200,"H":{"I":"5abc9ccf494765f3cac7c56b","T":"Германия (16)","XI":24791},"I":"5abc9cd4494765f3cac7fc52","P":[{"A":14,"H":19,"T":18},{"A":14,"H":15,"T":19},{"A":2,"H":13,"T":20},{"A":16,"H":16,"T":21}],"R":2,"S1":63,"S2":46,"SI":"5abc9cd3494765f3cac7fc38","St":3,"W":1},{"A":{"I":"5abc9cd1494765f3cac7d9cb","T":"Дания (16)","XI":25579},"D":1281709800,"H":{"I":"5abc9ccf494765f3cac7c569","T":"Латвия (16)","XI":22263},"I":"5abc9cd4494765f3cac7fc56","P":[{"A":11,"H":23,"T":18},{"A":9,"H":10,"T":19},{"A":9,"H":6,"T":20},{"A":18,"H":10,"T":21}],"R":1,"S1":49,"S2":47,"SI":"5abc9cd3494765f3cac7fc38","St":3,"W":1},{"A":{"I":"5abc9ccf494765f3cac7c6ae","T":"Израиль (16)","XI":25015},"D":1281528900,"H":{"I":"5abc9ccf494765f3cac7c569","T":"Латвия (16)","XI":22263},"I":"5abc9cd4494765f3cac7fc53","P":[{"A":18,"H":14,"T":18},{"A":10,"H":15,"T":19},{"A":14,"H":13,"T":20},{"A":16,"H":21,"T":21}],"R":1,"S1":63,"S2":58,"SI":"5abc9cd3494765f3cac7fc38","St":3},{"A":{"I":"5abc9ccf494765f3cac7c56b","T":"Германия (16)","XI":24791},"D":1281442500,"H":{"I":"5abc9ccf494765f3cac7c569","T":"Латвия (16)","XI":22263},"I":"5abc9cd4494765f3cac7fc57","P":[{"A":19,"H":16,"T":18},{"A":11,"H":14,"T":19},{"A":14,"H":7,"T":20},{"A":12,"H":17,"T":21}],"R":2,"S1":54,"S2":56,"SI":"5abc9cd3494765f3cac7fc38","St":3,"W":2}],"L":2,"M":2,"P":10,"S":0,"T":{"I":"5abc9ccf494765f3cac7c569","T":"Латвия (16)","XI":22263},"W":4},{"C":6,"D":0,"F":0,"G":[{"A":{"I":"5abc9ccf494765f3cac7c569","T":"Латвия (16)","XI":22263},"D":1281882600,"H":{"I":"5abc9ccf494765f3cac7c6ae","T":"Израиль (16)","XI":25015},"I":"5abc9cd4494765f3cac7fcc4","P":[{"A":15,"H":17,"T":18},{"A":18,"H":11,"T":19},{"A":14,"H":12,"T":20},{"A":18,"H":22,"T":21}],"R":2,"S1":62,"S2":65,"SI":"5abc9cd3494765f3cac7fc38","St":3},{"A":{"I":"5abc9ccf494765f3cac7c6ae","T":"Израиль (16)","XI":25015},"D":1281788100,"H":{"I":"5abc9cd1494765f3cac7d9cb","T":"Дания (16)","XI":25579},"I":"5abc9cd4494765f3cac7fc4f","P":[{"A":17,"H":7,"T":18},{"A":17,"H":18,"T":19},{"A":19,"H":16,"T":20},{"A":22,"H":21,"T":21}],"R":1,"S1":62,"S2":75,"SI":"5abc9cd3494765f3cac7fc38","St":3,"W":2},{"A":{"I":"5abc9ccf494765f3cac7c56b","T":"Германия (16)","XI":24791},"D":1281701700,"H":{"I":"5abc9ccf494765f3cac7c6ae","T":"Израиль (16)","XI":25015},"I":"5abc9cd4494765f3cac7fc99","P":[{"A":12,"H":11,"T":18},{"A":13,"H":17,"T":19},{"A":13,"H":12,"T":20},{"A":11,"H":20,"T":21}],"R":1,"S1":60,"S2":49,"SI":"5abc9cd3494765f3cac7fc38","St":3,"W":1},{"A":{"I":"5abc9ccf494765f3cac7c6ae","T":"Израиль (16)","XI":25015},"D":1281528900,"H":{"I":"5abc9ccf494765f3cac7c569","T":"Латвия (16)","XI":22263},"I":"5abc9cd4494765f3cac7fc53","P":[{"A":18,"H":14,"T":18},{"A":10,"H":15,"T":19},{"A":14,"H":13,"T":20},{"A":16,"H":21,"T":21}],"R":2,"S1":63,"S2":58,"SI":"5abc9cd3494765f3cac7fc38","St":3},{"A":{"I":"5abc9cd1494765f3cac7d9cb","T":"Дания (16)","XI":25579},"D":1281442500,"H":{"I":"5abc9ccf494765f3cac7c6ae","T":"Израиль (16)","XI":25015},"I":"5abc9cd4494765f3cac7fc55","P":[{"A":14,"H":8,"T":18},{"A":14,"H":30,"T":19},{"A":21,"H":9,"T":20},{"A":12,"H":16,"T":21}],"R":1,"S1":63,"S2":61,"SI":"5abc9cd3494765f3cac7fc38","St":3,"W":1}],"L":3,"M":3,"N":"Зона вылета","P":9,"S":0,"T":{"I":"5abc9ccf494765f3cac7c6ae","T":"Израиль (16)","XI":25015},"W":3},{"C":6,"D":0,"F":0,"G":[{"A":{"I":"5abc9ccf494765f3cac7c56b","T":"Германия (16)","XI":24791},"D":1281874500,"H":{"I":"5abc9cd1494765f3cac7d9cb","T":"Дания (16)","XI":25579},"I":"5abc9cd4494765f3cac7fc50","P":[{"A":18,"H":24,"T":18},{"A":17,"H":21,"T":19},{"A":18,"H":12,"T":20},{"A":19,"H":20,"T":21}],"R":1,"S1":77,"S2":72,"SI":"5abc9cd3494765f3cac7fc38","St":3,"W":1},{"A":{"I":"5abc9ccf494765f3cac7c6ae","T":"Израиль (16)","XI":25015},"D":1281788100,"H":{"I":"5abc9cd1494765f3cac7d9cb","T":"Дания (16)","XI":25579},"I":"5abc9cd4494765f3cac7fc4f","P":[{"A":17,"H":7,"T":18},{"A":17,"H":18,"T":19},{"A":19,"H":16,"T":20},{"A":22,"H":21,"T":21}],"R":2,"S1":62,"S2":75,"SI":"5abc9cd3494765f3cac7fc38","St":3,"W":2},{"A":{"I":"5abc9cd1494765f3cac7d9cb","T":"Дания (16)","XI":25579},"D":1281709800,"H":{"I":"5abc9ccf494765f3cac7c569","T":"Латвия (16)","XI":22263},"I":"5abc9cd4494765f3cac7fc56","P":[{"A":11,"H":23,"T":18},{"A":9,"H":10,"T":19},{"A":9,"H":6,"T":20},{"A":18,"H":10,"T":21}],"R":2,"S1":49,"S2":47,"SI":"5abc9cd3494765f3cac7fc38","St":3,"W":1},{"A":{"I":"5abc9cd1494765f3cac7d9cb","T":"Дания (16)","XI":25579},"D":1281528900,"H":{"I":"5abc9ccf494765f3cac7c56b","T":"Германия (16)","XI":24791},"I":"5abc9cd4494765f3cac7fc54","P":[{"A":7,"H":24,"T":18},{"A":13,"H":17,"T":19},{"A":11,"H":13,"T":20},{"A":9,"H":14,"T":21}],"R":2,"S1":68,"S2":40,"SI":"5abc9cd3494765f3cac7fc38","St":3,"W":1},{"A":{"I":"5abc9cd1494765f3cac7d9cb","T":"Дания (16)","XI":25579},"D":1281442500,"H":{"I":"5abc9ccf494765f3cac7c6ae","T":"Израиль (16)","XI":25015},"I":"5abc9cd4494765f3cac7fc55","P":[{"A":14,"H":8,"T":18},{"A":14,"H":30,"T":19},{"A":21,"H":9,"T":20},{"A":12,"H":16,"T":21}],"R":2,"S1":63,"S2":61,"SI":"5abc9cd3494765f3cac7fc38","St":3,"W":1}],"L":5,"M":4,"N":"Зона вылета","P":7,"S":0,"T":{"I":"5abc9cd1494765f3cac7d9cb","T":"Дания (16)","XI":25579},"W":1}],"T":"Группа G"}]}},{"C":{"I":223,"T":"Европа"},"H":false,"I":"5abc9cd5494765f3cac80869","N":"Чемпионат Европы до 16 лет","R":"5ab11d23494765f3ca230d91","T":1,"D":{"C":[{"A":{"I":"5abc9ccf494765f3cac7c66f","T":"Литва (16)","XI":24907},"C":{"A":{"I":"5abc9ccf494765f3cac7c666","T":"Испания (16)","XI":24855},"C":{"A":{"I":"5abc9ccf494765f3cac7c6ad","T":"Россия (16)","XI":24857},"G":[{"A":{"I":"5abc9ccf494765f3cac7c6ad","T":"Россия (16)","XI":24857},"D":1281701700,"H":{"I":"5abc9ccf494765f3cac7c66c","T":"Хорватия (16)","XI":24843},"I":"5abc9cd5494765f3cac80882","P":[{"A":16,"H":15,"T":18},{"A":20,"H":17,"T":19},{"A":14,"H":22,"T":20},{"A":15,"H":27,"T":21}],"S1":81,"S2":65,"SI":"5abc9cd5494765f3cac80869","St":3,"T":"Четвертьфиналы","W":1}],"H":{"I":"5abc9ccf494765f3cac7c66c","T":"Хорватия (16)","XI":24843},"T":"Четвертьфиналы"},"D":{"A":{"I":"5abc9ccf494765f3cac7c605","T":"Франция (16)","XI":24911},"G":[{"A":{"I":"5abc9ccf494765f3cac7c605","T":"Франция (16)","XI":24911},"D":1281717900,"H":{"I":"5abc9ccf494765f3cac7c666","T":"Испания (16)","XI":24855},"I":"5abc9cd5494765f3cac8087d","P":[{"A":18,"H":12,"T":18},{"A":12,"H":22,"T":19},{"A":12,"H":6,"T":20},{"A":14,"H":17,"T":21}],"S1":57,"S2":56,"SI":"5abc9cd5494765f3cac80869","St":3,"T":"Четвертьфиналы","W":1}],"H":{"I":"5abc9ccf494765f3cac7c666","T":"Испания (16)","XI":24855},"T":"Четвертьфиналы"},"G":[{"A":{"I":"5abc9ccf494765f3cac7c666","T":"Испания (16)","XI":24855},"D":1281804300,"H":{"I":"5abc9ccf494765f3cac7c66c","T":"Хорватия (16)","XI":24843},"I":"5abc9cd5494765f3cac8087f","P":[{"A":18,"H":22,"T":18},{"A":22,"H":15,"T":19},{"A":14,"H":18,"T":20},{"A":28,"H":31,"T":21}],"S1":86,"S2":82,"SI":"5abc9cd5494765f3cac80869","St":3,"T":"Полуфиналы","W":1}],"H":{"I":"5abc9ccf494765f3cac7c66c","T":"Хорватия (16)","XI":24843},"T":"Полуфиналы"},"D":{"A":{"I":"5abc9ccf494765f3cac7c66f","T":"Литва (16)","XI":24907},"C":{"A":{"I":"5abc9ccf494765f3cac7c664","T":"Турция (16)","XI":22265},"G":[{"A":{"I":"5abc9ccf494765f3cac7c664","T":"Турция (16)","XI":22265},"D":1281709800,"H":{"I":"5abc9ccf494765f3cac7c56c","T":"Сербия (16)","XI":24909},"I":"5abc9cd5494765f3cac80879","P":[{"A":12,"H":17,"T":18},{"A":9,"H":7,"T":19},{"A":30,"H":16,"T":20},{"A":13,"H":22,"T":21}],"S1":62,"S2":64,"SI":"5abc9cd5494765f3cac80869","St":3,"T":"Четвертьфиналы","W":2}],"H":{"I":"5abc9ccf494765f3cac7c56c","T":"Сербия (16)","XI":24909},"T":"Четвертьфиналы"},"D":{"A":{"I":"5abc9ccf494765f3cac7c66f","T":"Литва (16)","XI":24907},"G":[{"A":{"I":"5abc9ccf494765f3cac7c66f","T":"Литва (16)","XI":24907},"D":1281726000,"H":{"I":"5abc9ccf494765f3cac7c5fd","T":"Черногория (16)","XI":24847},"I":"5abc9cd5494765f3cac8087e","P":[{"A":10,"H":14,"T":18},{"A":18,"H":19,"T":19},{"A":12,"H":14,"T":20},{"A":16,"H":8,"T":21}],"S1":55,"S2":56,"SI":"5abc9cd5494765f3cac80869","St":3}],"H":{"I":"5abc9ccf494765f3cac7c5fd","T":"Черногория (16)","XI":24847},"T":"Четвертьфиналы"},"G":[{"A":{"I":"5abc9ccf494765f3cac7c66f","T":"Литва (16)","XI":24907},"D":1281812400,"H":{"I":"5abc9ccf494765f3cac7c664","T":"Турция (16)","XI":22265},"I":"5abc9cd5494765f3cac80883","P":[{"A":20,"H":12,"T":18},{"A":20,"H":13,"T":19},{"A":15,"H":14,"T":20},{"A":25,"H":26,"T":21}],"S1":65,"S2":80,"SI":"5abc9cd5494765f3cac80869","St":3,"T":"Полуфиналы","W":2}],"H":{"I":"5abc9ccf494765f3cac7c664","T":"Турция (16)","XI":22265},"T":"Полуфиналы"},"G":[{"A":{"I":"5abc9ccf494765f3cac7c66f","T":"Литва (16)","XI":24907},"D":1281898800,"H":{"I":"5abc9ccf494765f3cac7c66c","T":"Хорватия (16)","XI":24843},"I":"5abc9cd5494765f3cac8087c","P":[{"A":6,"H":30,"T":18},{"A":26,"H":17,"T":19},{"A":7,"H":18,"T":20},{"A":13,"H":15,"T":21}],"S1":80,"S2":52,"SI":"5abc9cd5494765f3cac80869","St":3,"T":"Финал","W":1}],"H":{"I":"5abc9ccf494765f3cac7c66c","T":"Хорватия (16)","XI":24843},"T":"Финал"}]}},{"C":{"I":223,"T":"Европа"},"H":false,"I":"5abc9cd5494765f3cac80776","N":"Чемпионат Европы до 16 лет","R":"5ab11d23494765f3ca230d91","T":2,"A":{"C":[{"R":[{"C":5,"D":0,"F":0,"G":[{"A":{"I":"5abc9ccf494765f3cac7c66c","T":"Хорватия (16)","XI":24843},"D":1281553200,"H":{"I":"5abc9ccf494765f3cac7c605","T":"Франция (16)","XI":24911},"I":"5abc9cd5494765f3cac80783","P":[{"A":18,"H":22,"T":18},{"A":15,"H":14,"T":19},{"A":18,"H":15,"T":20},{"A":12,"H":13,"T":21}],"R":2,"S1":64,"S2":63,"SI":"5abc9cd5494765f3cac80776","St":3,"W":1},{"A":{"I":"5abc9ccf494765f3cac7c66f","T":"Литва (16)","XI":24907},"D":1281466800,"H":{"I":"5abc9ccf494765f3cac7c66c","T":"Хорватия (16)","XI":24843},"I":"5abc9cd5494765f3cac807a2","P":[{"A":21,"H":24,"T":18},{"A":16,"H":12,"T":19},{"A":14,"H":15,"T":20},{"A":17,"H":27,"T":21}],"R":1,"S1":78,"S2":68,"SI":"5abc9cd5494765f3cac80776","St":3,"W":1},{"A":{"I":"5abc9ccf494765f3cac7c66c","T":"Хорватия (16)","XI":24843},"D":1281372300,"H":{"I":"5abc9ccf494765f3cac7c364","T":"Греция (16)","XI":24989},"I":"5abc9cd5494765f3cac8079e","P":[{"A":16,"H":13,"T":18},{"A":15,"H":13,"T":19},{"A":13,"H":14,"T":20},{"A":26,"H":9,"T":21}],"R":1,"S1":49,"S2":70,"SI":"5abc9cd5494765f3cac80776","St":3,"W":2}],"L":1,"M":1,"N":"Проход дальше - Чемпионат Европы до 16 лет (Плей-офф)","P":9,"S":0,"T":{"I":"5abc9ccf494765f3cac7c66c","T":"Хорватия (16)","XI":24843},"W":4},{"C":5,"D":0,"F":0,"G":[{"A":{"I":"5abc9ccf494765f3cac7c364","T":"Греция (16)","XI":24989},"D":1281537000,"H":{"I":"5abc9ccf494765f3cac7c56c","T":"Сербия (16)","XI":24909},"I":"5abc9cd5494765f3cac80787","P":[{"A":29,"H":27,"T":18},{"A":15,"H":19,"T":19},{"A":14,"H":14,"T":20},{"A":11,"H":22,"T":21}],"R":1,"S1":82,"S2":69,"SI":"5abc9cd5494765f3cac80776","St":3,"W":1},{"A":{"I":"5abc9ccf494765f3cac7c605","T":"Франция (16)","XI":24911},"D":1281458700,"H":{"I":"5abc9ccf494765f3cac7c56c","T":"Сербия (16)","XI":24909},"I":"5abc9cd5494765f3cac8078b","P":[{"A":10,"H":15,"T":18},{"A":15,"H":13,"T":19},{"A":14,"H":10,"T":20},{"A":16,"H":17,"T":21},{"A":6,"H":14,"T":4}],"R":1,"S1":69,"S2":61,"SI":"5abc9cd5494765f3cac80776","St":3,"W":1},{"A":{"I":"5abc9ccf494765f3cac7c56c","T":"Сербия (16)","XI":24909},"D":1281380400,"H":{"I":"5abc9ccf494765f3cac7c66f","T":"Литва (16)","XI":24907},"I":"5abc9cd5494765f3cac8079d","P":[{"A":15,"H":26,"T":18},{"A":18,"H":16,"T":19},{"A":18,"H":12,"T":20},{"A":25,"H":20,"T":21}],"R":1,"S1":74,"S2":76,"SI":"5abc9cd5494765f3cac80776","St":3}],"L":1,"M":2,"N":"Проход дальше - Чемпионат Европы до 16 лет (Плей-офф)","P":9,"S":0,"T":{"I":"5abc9ccf494765f3cac7c56c","T":"Сербия (16)","XI":24909},"W":4},{"C":5,"D":0,"F":0,"G":[{"A":{"I":"5abc9ccf494765f3cac7c66c","T":"Хорватия (16)","XI":24843},"D":1281553200,"H":{"I":"5abc9ccf494765f3cac7c605","T":"Франция (16)","XI":24911},"I":"5abc9cd5494765f3cac80783","P":[{"A":18,"H":22,"T":18},{"A":15,"H":14,"T":19},{"A":18,"H":15,"T":20},{"A":12,"H":13,"T":21}],"R":1,"S1":64,"S2":63,"SI":"5abc9cd5494765f3cac80776","St":3,"W":1},{"A":{"I":"5abc9ccf494765f3cac7c605","T":"Франция (16)","XI":24911},"D":1281458700,"H":{"I":"5abc9ccf494765f3cac7c56c","T":"Сербия (16)","XI":24909},"I":"5abc9cd5494765f3cac8078b","P":[{"A":10,"H":15,"T":18},{"A":15,"H":13,"T":19},{"A":14,"H":10,"T":20},{"A":16,"H":17,"T":21},{"A":6,"H":14,"T":4}],"R":2,"S1":69,"S2":61,"SI":"5abc9cd5494765f3cac80776","St":3,"W":1},{"A":{"I":"5abc9ccf494765f3cac7c605","T":"Франция (16)","XI":24911},"D":1281364200,"H":{"I":"5abc9ccf494765f3cac7c5fc","T":"Италия (16)","XI":24839},"I":"5abc9cd5494765f3cac807a0","P":[{"A":26,"H":21,"T":18},{"A":9,"H":16,"T":19},{"A":13,"H":9,"T":20},{"A":19,"H":19,"T":21}],"R":1,"S1":65,"S2":67,"SI":"5abc9cd5494765f3cac80776","St":3}],"L":1,"M":3,"N":"Проход дальше - Чемпионат Европы до 16 лет (Плей-офф)","P":9,"S":0,"T":{"I":"5abc9ccf494765f3cac7c605","T":"Франция (16)","XI":24911},"W":4},{"C":5,"D":0,"F":0,"G":[{"A":{"I":"5abc9ccf494765f3cac7c5fc","T":"Италия (16)","XI":24839},"D":1281545100,"H":{"I":"5abc9ccf494765f3cac7c66f","T":"Литва (16)","XI":24907},"I":"5abc9cd5494765f3cac80789","P":[{"A":19,"H":26,"T":18},{"A":9,"H":16,"T":19},{"A":17,"H":12,"T":20},{"A":16,"H":26,"T":21}],"R":1,"S1":80,"S2":61,"SI":"5abc9cd5494765f3cac80776","St":3,"W":1},{"A":{"I":"5abc9ccf494765f3cac7c66f","T":"Литва (16)","XI":24907},"D":1281466800,"H":{"I":"5abc9ccf494765f3cac7c66c","T":"Хорватия (16)","XI":24843},"I":"5abc9cd5494765f3cac807a2","P":[{"A":21,"H":24,"T":18},{"A":16,"H":12,"T":19},{"A":14,"H":15,"T":20},{"A":17,"H":27,"T":21}],"R":2,"S1":78,"S2":68,"SI":"5abc9cd5494765f3cac80776","St":3,"W":1},{"A":{"I":"5abc9ccf494765f3cac7c56c","T":"Сербия (16)","XI":24909},"D":1281380400,"H":{"I":"5abc9ccf494765f3cac7c66f","T":"Литва (16)","XI":24907},"I":"5abc9cd5494765f3cac8079d","P":[{"A":15,"H":26,"T":18},{"A":18,"H":16,"T":19},{"A":18,"H":12,"T":20},{"A":25,"H":20,"T":21}],"R":2,"S1":74,"S2":76,"SI":"5abc9cd5494765f3cac80776","St":3}],"L":4,"M":4,"N":"Проход дальше - Чемпионат Европы до 16 лет (Плей-офф)","P":6,"S":0,"T":{"I":"5abc9ccf494765f3cac7c66f","T":"Литва (16)","XI":24907},"W":1},{"C":5,"D":0,"F":0,"G":[{"A":{"I":"5abc9ccf494765f3cac7c5fc","T":"Италия (16)","XI":24839},"D":1281545100,"H":{"I":"5abc9ccf494765f3cac7c66f","T":"Литва (16)","XI":24907},"I":"5abc9cd5494765f3cac80789","P":[{"A":19,"H":26,"T":18},{"A":9,"H":16,"T":19},{"A":17,"H":12,"T":20},{"A":16,"H":26,"T":21}],"R":2,"S1":80,"S2":61,"SI":"5abc9cd5494765f3cac80776","St":3,"W":1},{"A":{"I":"5abc9ccf494765f3cac7c5fc","T":"Италия (16)","XI":24839},"D":1281450600,"H":{"I":"5abc9ccf494765f3cac7c364","T":"Греция (16)","XI":24989},"I":"5abc9cd5494765f3cac8079b","P":[{"A":23,"H":19,"T":18},{"A":14,"H":12,"T":19},{"A":13,"H":19,"T":20},{"A":21,"H":9,"T":21}],"R":1,"S1":59,"S2":71,"SI":"5abc9cd5494765f3cac80776","St":3,"W":2},{"A":{"I":"5abc9ccf494765f3cac7c605","T":"Франция (16)","XI":24911},"D":1281364200,"H":{"I":"5abc9ccf494765f3cac7c5fc","T":"Италия (16)","XI":24839},"I":"5abc9cd5494765f3cac807a0","P":[{"A":26,"H":21,"T":18},{"A":9,"H":16,"T":19},{"A":13,"H":9,"T":20},{"A":19,"H":19,"T":21}],"R":2,"S1":65,"S2":67,"SI":"5abc9cd5494765f3cac80776","St":3}],"L":4,"M":5,"N":"Евробаскет U16 (9-12 места)(Stat)","P":6,"S":0,"T":{"I":"5abc9ccf494765f3cac7c5fc","T":"Италия (16)","XI":24839},"W":1},{"C":5,"D":0,"F":0,"G":[{"A":{"I":"5abc9ccf494765f3cac7c364","T":"Греция (16)","XI":24989},"D":1281537000,"H":{"I":"5abc9ccf494765f3cac7c56c","T":"Сербия (16)","XI":24909},"I":"5abc9cd5494765f3cac80787","P":[{"A":29,"H":27,"T":18},{"A":15,"H":19,"T":19},{"A":14,"H":14,"T":20},{"A":11,"H":22,"T":21}],"R":2,"S1":82,"S2":69,"SI":"5abc9cd5494765f3cac80776","St":3,"W":1},{"A":{"I":"5abc9ccf494765f3cac7c5fc","T":"Италия (16)","XI":24839},"D":1281450600,"H":{"I":"5abc9ccf494765f3cac7c364","T":"Греция (16)","XI":24989},"I":"5abc9cd5494765f3cac8079b","P":[{"A":23,"H":19,"T":18},{"A":14,"H":12,"T":19},{"A":13,"H":19,"T":20},{"A":21,"H":9,"T":21}],"R":2,"S1":59,"S2":71,"SI":"5abc9cd5494765f3cac80776","St":3,"W":2},{"A":{"I":"5abc9ccf494765f3cac7c66c","T":"Хорватия (16)","XI":24843},"D":1281372300,"H":{"I":"5abc9ccf494765f3cac7c364","T":"Греция (16)","XI":24989},"I":"5abc9cd5494765f3cac8079e","P":[{"A":16,"H":13,"T":18},{"A":15,"H":13,"T":19},{"A":13,"H":14,"T":20},{"A":26,"H":9,"T":21}],"R":2,"S1":49,"S2":70,"SI":"5abc9cd5494765f3cac80776","St":3,"W":2}],"L":4,"M":6,"N":"Евробаскет U16 (9-12 места)(Stat)","P":6,"S":0,"T":{"I":"5abc9ccf494765f3cac7c364","T":"Греция (16)","XI":24989},"W":1}],"T":"Группа E"},{"R":[{"C":5,"D":0,"F":0,"G":[{"A":{"I":"5abc9ccf494765f3cac7c666","T":"Испания (16)","XI":24855},"D":1281553200,"H":{"I":"5abc9ccf494765f3cac7c5fd","T":"Черногория (16)","XI":24847},"I":"5abc9cd5494765f3cac80781","P":[{"A":14,"H":21,"T":18},{"A":21,"H":9,"T":19},{"A":8,"H":14,"T":20},{"A":20,"H":24,"T":21}],"R":2,"S1":68,"S2":63,"SI":"5abc9cd5494765f3cac80776","St":3},{"A":{"I":"5abc9ccf494765f3cac7c664","T":"Турция (16)","XI":22265},"D":1281450600,"H":{"I":"5abc9ccf494765f3cac7c666","T":"Испания (16)","XI":24855},"I":"5abc9cd5494765f3cac80788","P":[{"A":23,"H":23,"T":18},{"A":17,"H":21,"T":19},{"A":13,"H":16,"T":20},{"A":16,"H":14,"T":21}],"R":1,"S1":74,"S2":69,"SI":"5abc9cd5494765f3cac80776","St":3,"W":1},{"A":{"I":"5abc9ccf494765f3cac7c666","T":"Испания (16)","XI":24855},"D":1281372300,"H":{"I":"5abc9ccf494765f3cac7c6ad","T":"Россия (16)","XI":24857},"I":"5abc9cd5494765f3cac8079f","P":[{"A":21,"H":17,"T":18},{"A":18,"H":8,"T":19},{"A":22,"H":14,"T":20},{"A":16,"H":26,"T":21}],"R":1,"S1":65,"S2":77,"SI":"5abc9cd5494765f3cac80776","St":3,"W":2}],"L":1,"M":1,"N":"Проход дальше - Чемпионат Европы до 16 лет (Плей-офф)","P":9,"S":0,"T":{"I":"5abc9ccf494765f3cac7c666","T":"Испания (16)","XI":24855},"W":4},{"C":5,"D":0,"F":0,"G":[{"A":{"I":"5abc9ccf494765f3cac7c666","T":"Испания (16)","XI":24855},"D":1281553200,"H":{"I":"5abc9ccf494765f3cac7c5fd","T":"Черногория (16)","XI":24847},"I":"5abc9cd5494765f3cac80781","P":[{"A":14,"H":21,"T":18},{"A":21,"H":9,"T":19},{"A":8,"H":14,"T":20},{"A":20,"H":24,"T":21}],"R":1,"S1":68,"S2":63,"SI":"5abc9cd5494765f3cac80776","St":3},{"A":{"I":"5abc9ccf494765f3cac7c5fd","T":"Черногория (16)","XI":24847},"D":1281466800,"H":{"I":"5abc9cd3494765f3cac7fb18","T":"Болгария (16)","XI":24919},"I":"5abc9cd5494765f3cac80782","P":[{"A":15,"H":19,"T":18},{"A":14,"H":14,"T":19},{"A":13,"H":19,"T":20},{"A":19,"H":20,"T":21}],"R":2,"S1":72,"S2":61,"SI":"5abc9cd5494765f3cac80776","St":3,"W":1},{"A":{"I":"5abc9ccf494765f3cac7c5fd","T":"Черногория (16)","XI":24847},"D":1281380400,"H":{"I":"5abc9ccf494765f3cac7c35f","T":"Польша (16)","XI":24849},"I":"5abc9cd5494765f3cac8079c","P":[{"A":24,"H":23,"T":18},{"A":33,"H":20,"T":19},{"A":19,"H":14,"T":20},{"A":19,"H":12,"T":21}],"R":1,"S1":69,"S2":95,"SI":"5abc9cd5494765f3cac80776","St":3,"W":2}],"L":1,"M":2,"N":"Проход дальше - Чемпионат Европы до 16 лет (Плей-офф)","P":9,"S":0,"T":{"I":"5abc9ccf494765f3cac7c5fd","T":"Черногория (16)","XI":24847},"W":4},{"C":5,"D":0,"F":0,"G":[{"A":{"I":"5abc9ccf494765f3cac7c35f","T":"Польша (16)","XI":24849},"D":1281545100,"H":{"I":"5abc9ccf494765f3cac7c664","T":"Турция (16)","XI":22265},"I":"5abc9cd5494765f3cac80785","P":[{"A":11,"H":28,"T":18},{"A":12,"H":17,"T":19},{"A":19,"H":16,"T":20},{"A":18,"H":28,"T":21}],"R":1,"S1":89,"S2":60,"SI":"5abc9cd5494765f3cac80776","St":3,"W":1},{"A":{"I":"5abc9ccf494765f3cac7c664","T":"Турция (16)","XI":22265},"D":1281450600,"H":{"I":"5abc9ccf494765f3cac7c666","T":"Испания (16)","XI":24855},"I":"5abc9cd5494765f3cac80788","P":[{"A":23,"H":23,"T":18},{"A":17,"H":21,"T":19},{"A":13,"H":16,"T":20},{"A":16,"H":14,"T":21}],"R":2,"S1":74,"S2":69,"SI":"5abc9cd5494765f3cac80776","St":3,"W":1},{"A":{"I":"5abc9cd3494765f3cac7fb18","T":"Болгария (16)","XI":24919},"D":1281364200,"H":{"I":"5abc9ccf494765f3cac7c664","T":"Турция (16)","XI":22265},"I":"5abc9cd5494765f3cac8079a","P":[{"A":16,"H":22,"T":18},{"A":13,"H":17,"T":19},{"A":13,"H":19,"T":20},{"A":18,"H":19,"T":21}],"R":1,"S1":77,"S2":60,"SI":"5abc9cd5494765f3cac80776","St":3,"W":1}],"L":2,"M":3,"N":"Проход дальше - Чемпионат Европы до 16 лет (Плей-офф)","P":8,"S":0,"T":{"I":"5abc9ccf494765f3cac7c664","T":"Турция (16)","XI":22265},"W":3},{"C":5,"D":0,"F":0,"G":[{"A":{"I":"5abc9ccf494765f3cac7c6ad","T":"Россия (16)","XI":24857},"D":1281537000,"H":{"I":"5abc9cd3494765f3cac7fb18","T":"Болгария (16)","XI":24919},"I":"5abc9cd5494765f3cac80786","P":[{"A":12,"H":10,"T":18},{"A":8,"H":14,"T":19},{"A":27,"H":17,"T":20},{"A":17,"H":8,"T":21}],"R":1,"S1":49,"S2":64,"SI":"5abc9cd5494765f3cac80776","St":3,"W":2},{"A":{"I":"5abc9ccf494765f3cac7c35f","T":"Польша (16)","XI":24849},"D":1281458700,"H":{"I":"5abc9ccf494765f3cac7c6ad","T":"Россия (16)","XI":24857},"I":"5abc9cd5494765f3cac80784","P":[{"A":32,"H":19,"T":18},{"A":12,"H":30,"T":19},{"A":21,"H":27,"T":20},{"A":22,"H":13,"T":21}],"R":1,"S1":89,"S2":87,"SI":"5abc9cd5494765f3cac80776","St":3,"W":1},{"A":{"I":"5abc9ccf494765f3cac7c666","T":"Испания (16)","XI":24855},"D":1281372300,"H":{"I":"5abc9ccf494765f3cac7c6ad","T":"Россия (16)","XI":24857},"I":"5abc9cd5494765f3cac8079f","P":[{"A":21,"H":17,"T":18},{"A":18,"H":8,"T":19},{"A":22,"H":14,"T":20},{"A":16,"H":26,"T":21}],"R":2,"S1":65,"S2":77,"SI":"5abc9cd5494765f3cac80776","St":3,"W":2}],"L":3,"M":4,"N":"Проход дальше - Чемпионат Европы до 16 лет (Плей-офф)","P":7,"S":0,"T":{"I":"5abc9ccf494765f3cac7c6ad","T":"Россия (16)","XI":24857},"W":2},{"C":5,"D":0,"F":0,"G":[{"A":{"I":"5abc9ccf494765f3cac7c6ad","T":"Россия (16)","XI":24857},"D":1281537000,"H":{"I":"5abc9cd3494765f3cac7fb18","T":"Болгария (16)","XI":24919},"I":"5abc9cd5494765f3cac80786","P":[{"A":12,"H":10,"T":18},{"A":8,"H":14,"T":19},{"A":27,"H":17,"T":20},{"A":17,"H":8,"T":21}],"R":2,"S1":49,"S2":64,"SI":"5abc9cd5494765f3cac80776","St":3,"W":2},{"A":{"I":"5abc9ccf494765f3cac7c5fd","T":"Черногория (16)","XI":24847},"D":1281466800,"H":{"I":"5abc9cd3494765f3cac7fb18","T":"Болгария (16)","XI":24919},"I":"5abc9cd5494765f3cac80782","P":[{"A":15,"H":19,"T":18},{"A":14,"H":14,"T":19},{"A":13,"H":19,"T":20},{"A":19,"H":20,"T":21}],"R":1,"S1":72,"S2":61,"SI":"5abc9cd5494765f3cac80776","St":3,"W":1},{"A":{"I":"5abc9cd3494765f3cac7fb18","T":"Болгария (16)","XI":24919},"D":1281364200,"H":{"I":"5abc9ccf494765f3cac7c664","T":"Турция (16)","XI":22265},"I":"5abc9cd5494765f3cac8079a","P":[{"A":16,"H":22,"T":18},{"A":13,"H":17,"T":19},{"A":13,"H":19,"T":20},{"A":18,"H":19,"T":21}],"R":2,"S1":77,"S2":60,"SI":"5abc9cd5494765f3cac80776","St":3,"W":1}],"L":3,"M":5,"N":"Евробаскет U16 (9-12 места)(Stat)","P":7,"S":0,"T":{"I":"5abc9cd3494765f3cac7fb18","T":"Болгария (16)","XI":24919},"W":2},{"C":5,"D":0,"F":0,"G":[{"A":{"I":"5abc9ccf494765f3cac7c35f","T":"Польша (16)","XI":24849},"D":1281545100,"H":{"I":"5abc9ccf494765f3cac7c664","T":"Турция (16)","XI":22265},"I":"5abc9cd5494765f3cac80785","P":[{"A":11,"H":28,"T":18},{"A":12,"H":17,"T":19},{"A":19,"H":16,"T":20},{"A":18,"H":28,"T":21}],"R":2,"S1":89,"S2":60,"SI":"5abc9cd5494765f3cac80776","St":3,"W":1},{"A":{"I":"5abc9ccf494765f3cac7c35f","T":"Польша (16)","XI":24849},"D":1281458700,"H":{"I":"5abc9ccf494765f3cac7c6ad","T":"Россия (16)","XI":24857},"I":"5abc9cd5494765f3cac80784","P":[{"A":32,"H":19,"T":18},{"A":12,"H":30,"T":19},{"A":21,"H":27,"T":20},{"A":22,"H":13,"T":21}],"R":2,"S1":89,"S2":87,"SI":"5abc9cd5494765f3cac80776","St":3,"W":1},{"A":{"I":"5abc9ccf494765f3cac7c5fd","T":"Черногория (16)","XI":24847},"D":1281380400,"H":{"I":"5abc9ccf494765f3cac7c35f","T":"Польша (16)","XI":24849},"I":"5abc9cd5494765f3cac8079c","P":[{"A":24,"H":23,"T":18},{"A":33,"H":20,"T":19},{"A":19,"H":14,"T":20},{"A":19,"H":12,"T":21}],"R":2,"S1":69,"S2":95,"SI":"5abc9cd5494765f3cac80776","St":3,"W":2}],"L":5,"M":6,"N":"Евробаскет U16 (9-12 места)(Stat)","P":5,"S":0,"T":{"I":"5abc9ccf494765f3cac7c35f","T":"Польша (16)","XI":24849},"W":0}],"T":"Группа F"}]}}],"SI":3,"T":{"I":"5abc9ccf494765f3cac7c357","T":"Евробаскет U16"}},"t":{"255":"Этап","68":"Сезон","126":"Шахматка","42":"Турнирная таблица","389":"Информация","1":"Следующие матчи","2":"Предыдущие матчи","43":"Турнирная сетка","150":"Выберите сезон","44":"И ","45":"Игр","46":"В ","47":"Выигрыши","48":"Н ","49":"Ничья","50":"П ","51":"Поражений","52":"ЗМ","53":"Забито мячей","54":"ПМ","55":"Пропущено мячей","56":"РМ","57":"Разница мячей","58":"Очки","59":"Форма","60":"Команда","61":"Все","62":"Свернуть"}}