{"statistic":{"FG":[],"G":{"I":"5ab11d65494765f3ca2315c8","T":"2017"},"LG":[],"N":[{"I":"5ab11d10494765f3ca230666","T":"2018"},{"I":"5ab11d65494765f3ca2315c8","T":"2017"},{"I":"5ab11ddb494765f3ca232d74","T":"2016"},{"I":"5ab11e35494765f3ca235393","T":"2015"},{"I":"5ab11e85494765f3ca2367ff","T":"2014"},{"I":"5ab12632494765f3ca23fb68","T":"2013"},{"I":"5ab11d18494765f3ca23071a","T":"2012"},{"I":"5ab11d23494765f3ca230e27","T":"2011"}],"S":[{"C":{"I":153,"T":"США"},"H":false,"I":"5abc9f06494765f3cad4d45b","N":"NCAA","R":"5ab11d1b494765f3ca23077e","T":1,"D":{"C":[{"A":{"I":"5abc9f03494765f3cad4c811","T":"Техас A&M Корпус Кристи","XI":153447},"C":{"A":{"I":"5abc9f06494765f3cad4d46b","T":"Фурмaн Паладинс","XI":7498},"C":{"A":{"I":"5abc9f06494765f3cad4d472","T":"Сент Петерс Пикокс","XI":7364},"C":{"A":{"I":"5abc9b71494765f3cabe0ae4","T":"Айдахо Вандалс","XI":7588},"C":{"A":{"I":"5abc9f06494765f3cad4d470","T":"Ламар Кардинлз","XI":7508},"G":[null],"H":{"I":"5abc9f06494765f3cad4d466","T":"Техас Стейт Бобкэтс","XI":7598},"T":"1\/16"},"D":{"A":{"I":"5abc9b71494765f3cabe0ae4","T":"Айдахо Вандалс","XI":7588},"G":[null],"H":{"I":"5ab7e936494765f3ca75058d","T":"Стефан Ф. Остин Ламберджекс","XI":7522},"T":"1\/16"},"G":[null],"H":{"I":"5abc9f06494765f3cad4d466","T":"Техас Стейт Бобкэтс","XI":7598},"T":"1\/8 финала"},"D":{"C":{"A":{"I":"5abc9b71494765f3cabe0b03","T":"Олбани","XI":128849},"G":[null],"H":{"I":"5abc9f06494765f3cad4d472","T":"Сент Петерс Пикокс","XI":7364},"T":"1\/16"},"D":{"G":[],"T":"1\/16"},"G":[],"H":{"I":"5abc9f06494765f3cad4d472","T":"Сент Петерс Пикокс","XI":7364},"T":"1\/8 финала"},"G":[null],"H":{"I":"5abc9f06494765f3cad4d466","T":"Техас Стейт Бобкэтс","XI":7598},"T":"Четвертьфиналы"},"D":{"A":{"I":"5abc9f06494765f3cad4d46b","T":"Фурмaн Паладинс","XI":7498},"C":{"A":{"I":"5abc9f06494765f3cad4d346","T":"Теннесси Мартин Скайхокс","XI":128009},"C":{"A":{"I":"5abc9b71494765f3cabe0ae6","T":"Хьюстон Баптист Хаскис","XI":7300},"G":[null],"H":{"I":"5ab11dd8494765f3ca232d1a","T":"Кэмпбелл Файтинг Кэмелс","XI":7268},"T":"1\/16"},"D":{"A":{"I":"5abc9f06494765f3cad4d346","T":"Теннесси Мартин Скайхокс","XI":128009},"G":[null],"H":{"I":"5abc9f06494765f3cad4d46a","T":"УНК Эшвилл Буллдогз","XI":7264},"T":"1\/16"},"G":[null],"H":{"I":"5ab11dd8494765f3ca232d1a","T":"Кэмпбелл Файтинг Кэмелс","XI":7268},"T":"1\/8 финала"},"D":{"C":{"A":{"I":"5abc9f03494765f3cad4c852","T":"УСК Апстейт Спартанс","XI":7230},"G":[null],"H":{"I":"5abc9f06494765f3cad4d46b","T":"Фурмaн Паладинс","XI":7498},"T":"1\/16"},"D":{"G":[],"T":"1\/16"},"G":[],"H":{"I":"5abc9f06494765f3cad4d46b","T":"Фурмaн Паладинс","XI":7498},"T":"1\/8 финала"},"G":[null],"H":{"I":"5ab11dd8494765f3ca232d1a","T":"Кэмпбелл Файтинг Кэмелс","XI":7268},"T":"Четвертьфиналы"},"G":[null],"H":{"I":"5abc9f06494765f3cad4d472","T":"Сент Петерс Пикокс","XI":7364},"T":"Полуфиналы"},"D":{"A":{"I":"5abc9f03494765f3cad4c811","T":"Техас A&M Корпус Кристи","XI":153447},"C":{"A":{"I":"5ab29e22494765f3ca375655","T":"Либерти Флеймс","XI":6912},"C":{"A":{"I":"5abc9f06494765f3cad4d33c","T":"Сейнт Франсис Ред Флэш","XI":7436},"C":{"A":{"I":"5abc9f06494765f3cad4d49e","T":"Фэрфилд Стагс","XI":7348},"G":[null],"H":{"I":"5ab45b3e494765f3ca49caf8","T":"УМБК","XI":7206},"T":"1\/16"},"D":{"A":{"I":"5abc9f06494765f3cad4d33c","T":"Сейнт Франсис Ред Флэш","XI":7436},"G":[null],"H":{"I":"5abc9f06494765f3cad4d489","T":"Джексонвилл Долфинз","XI":7218},"T":"1\/16"},"G":[null],"H":{"I":"5ab45b3e494765f3ca49caf8","T":"УМБК","XI":7206},"T":"1\/8 финала"},"D":{"A":{"I":"5abc9f06494765f3cad4d467","T":"Самфорд","XI":127969},"C":{"A":{"I":"5abc9f03494765f3cad4c80a","T":"Норфолк Стэйт","XI":7406},"G":[null],"H":{"I":"5ab29e22494765f3ca375655","T":"Либерти Флеймс","XI":6912},"T":"1\/16"},"D":{"A":{"I":"5abc9f06494765f3cad4d467","T":"Самфорд","XI":127969},"G":[null],"H":{"I":"5abc9b72494765f3cabe11f3","T":"Канисиус Голдэн Гриффинс","XI":7346},"T":"1\/16"},"G":[null],"H":{"I":"5ab29e22494765f3ca375655","T":"Либерти Флеймс","XI":6912},"T":"1\/8 финала"},"G":[null],"H":{"I":"5ab45b3e494765f3ca49caf8","T":"УМБК","XI":7206},"T":"Четвертьфиналы"},"D":{"A":{"I":"5abc9f03494765f3cad4c7fb","T":"ИПФВ Мастандонт","XI":7526},"C":{"A":{"I":"5abc9b71494765f3cabe0c44","T":"Уэбер Стэйт Уайлдкэтс","XI":7254},"C":{"A":{"I":"5abc9f06494765f3cad4d469","T":"Джорджия Стэйт Пантерс","XI":7180},"G":[null],"H":{"I":"5abc9f03494765f3cad4c811","T":"Техас A&M Корпус Кристи","XI":153447},"T":"1\/16"},"D":{"A":{"I":"5abc9b71494765f3cabe0c44","T":"Уэбер Стэйт Уайлдкэтс","XI":7254},"G":[null],"H":{"I":"5abc9f06494765f3cad4d490","T":"Кал Стэйт Фуллертон Титанс","XI":7280},"T":"1\/16"},"G":[null],"H":{"I":"5abc9f03494765f3cad4c811","T":"Техас A&M Корпус Кристи","XI":153447},"T":"1\/8 финала"},"D":{"C":{"A":{"I":"5abc9f06494765f3cad4d46d","T":"Болл Стэйт Кардиналс","XI":128489},"G":[null],"H":{"I":"5abc9f03494765f3cad4c7fb","T":"ИПФВ Мастандонт","XI":7526},"T":"1\/16"},"D":{"G":[],"T":"1\/16"},"G":[],"H":{"I":"5abc9f03494765f3cad4c7fb","T":"ИПФВ Мастандонт","XI":7526},"T":"1\/8 финала"},"G":[null],"H":{"I":"5abc9f03494765f3cad4c811","T":"Техас A&M Корпус Кристи","XI":153447},"T":"Четвертьфиналы"},"G":[null],"H":{"I":"5ab45b3e494765f3ca49caf8","T":"УМБК","XI":7206},"T":"Полуфиналы"},"G":[null],"H":{"I":"5abc9f06494765f3cad4d472","T":"Сент Петерс Пикокс","XI":7364},"T":"Финал"}]}}],"SI":3,"T":{"I":"5ab11dc7494765f3ca232b4a","T":"CIT"}},"t":{"255":"Этап","68":"Сезон","126":"Шахматка","42":"Турнирная таблица","389":"Информация","1":"Следующие матчи","2":"Предыдущие матчи","43":"Турнирная сетка","150":"Выберите сезон","44":"И ","45":"Игр","46":"В ","47":"Выигрыши","48":"Н ","49":"Ничья","50":"П ","51":"Поражений","52":"ЗМ","53":"Забито мячей","54":"ПМ","55":"Пропущено мячей","56":"РМ","57":"Разница мячей","58":"Очки","59":"Форма","60":"Команда","61":"Все","62":"Свернуть"}}